Workbook
Name 、6: #REF!
Name \I: #REF!
Name \P: #REF!
Name _1: #REF!
Name _200901: #REF!
Name _200902: #REF!
Name _20090202: #REF!
Name _200903: #REF!
Name _20090303: #REF!
Name _200904: #REF!
Name _200910: #REF!
Name _200911: #REF!
Name _200912: #REF!
Name _20091201: #REF!
Name _908: #REF!
Name _AfA1: #REF!
Name _AfA10: #REF!
Name _AfA11: #REF!
Name _AfA12: #REF!
Name _AfA2: #REF!
Name _AfA3: #REF!
Name _AfA4: #REF!
Name _AfA5: #REF!
Name _AfA6: #REF!
Name _AfA7: #REF!
Name _AfA8: #REF!
Name _AfA9: #REF!
Name _DAT1: #REF!
Name _DAT10: #REF!
Name _DAT11: #REF!
Name _DAT12: #REF!
Name _DAT14: #REF!
Name _DAT15: #REF!
Name _DAT16: #REF!
Name _DAT17: #REF!
Name _DAT18: #REF!
Name _DAT19: #REF!
Name _DAT2: #REF!
Name _DAT20: #REF!
Name _DAT21: #REF!
Name _DAT22: #REF!
Name _DAT23: #REF!
Name _DAT24: #REF!
Name _DAT25: #REF!
Name _DAT26: #REF!
Name _DAT27: #REF!
Name _DAT28: #REF!
Name _DAT29: #REF!
Name _DAT3: #REF!
Name _DAT30: #REF!
Name _DAT31: #REF!
Name _DAT32: #REF!
Name _DAT33: #REF!
Name _DAT34: #REF!
Name _DAT35: #REF!
Name _DAT36: #REF!
Name _DAT37: #REF!
Name _DAT38: #REF!
Name _DAT39: #REF!
Name _DAT4: #REF!

Sheet 8月
A1: 8月 | R1: 利润（万元） | S1: 边际条件设定（必填项*） | AL1: 注意：此列往右禁止删除列
A2: 单位 | B2: 煤种 | C2: 热值 | D2: 单价 | E2: 价格 (元/吨) | F2: 收到基全水分% | G2: 收到基灰分% | H2: 收到基硫分% | I2: 收到基挥发分% | J2: 配煤比例 | K2: 规划用量 | L2: 可用量 | M2: 最低用量 | N2: 不含运费金额 | O2: 运费 | P2: 运费单价（元/吨） | Q2: 总金额 | R2: =C109 -> 6708.5566 | S2: 项目 | T2: 规划后值 | U2: 边际上限 | V2: 边际下限 | W2: 边际相等
A3: 百矿 | B3: =$B$112 -> 东怀 | C3: =INDEX($B$111:$Q$131,MATCH($B3,$B$111:$B$131,0),MATCH(C$2,$B$111:$Q$111,0)) -> 2482.3501 | D3: {=INDEX($B$111:$Q$131,MATCH($B3,$B$111:$B$131,0),COLUMN($D$2)-1)} -> 0.12049076 | E3: =C3*D3 -> 299.10026 | F3: =INDEX($B$111:$Q$131,MATCH($B3,$B$111:$B$131,0),MATCH(F$2,$B$111:$Q$111,0)) -> 9.05 | G3: =INDEX($B$111:$Q$131,MATCH($B3,$B$111:$B$131,0),MATCH(G$2,$B$111:$Q$111,0)) -> 53.753421 | H3: =INDEX($B$111:$Q$131,MATCH($B3,$B$111:$B$131,0),MATCH(H$2,$B$111:$Q$111,0)) -> 1.5392982 | I3: =INDEX($B$111:$Q$131,MATCH($B3,$B$111:$B$131,0),MATCH(I$2,$B$111:$Q$111,0)) -> 20.240833 | J3: =IFERROR(K3/K18*100,) -> 48.82006 | K3: 16.550016 | L3: {=LOOKUP(1,0/($B$111:$B$131=$B3),$L$111:$L$131)} -> 16.550016 | M3: 0 | N3: =IF(P3>0,INDEX($B$111:$Z$131,MATCH(B3,$B$111:$B$131,0),MATCH($Z$111,$B$111:$Z$111,0))*C3*K3,C3*D3*K3) -> 4724.5373 | O3: =P3*K3 -> 225.57672 | P3: {=INDEX($B$111:$AF$131,MATCH($B3,$B$111:$B$131,0),COLUMN($AA$111)-1)} -> 13.63 | Q3: =SUM(N3:O3) -> 4950.114 | S3: 原煤量 | T3: =$K$18 -> 33.900032 | U3: =W3 -> 33.900032 | V3: =W3 -> 33.900032 | W3: =$AP$164 -> 33.900032 | Z3: 单位 | AA3: 煤种 | AB3: 单价 | AC3: 热值 | AD3: 用量 | AE3: 金额
A4: 发电量 | B4: =$B$113 -> 跃进 | C4: =INDEX($B$111:$Q$131,MATCH($B4,$B$111:$B$131,0),MATCH(C$2,$B$111:$Q$111,0)) -> 1800 | D4: {=INDEX($B$111:$Q$131,MATCH($B4,$B$111:$B$131,0),COLUMN($D$2)-1)} -> 0.11937778 | E4: =C4*D4 -> 214.88 | F4: =INDEX($B$111:$Q$131,MATCH($B4,$B$111:$B$131,0),MATCH(F$2,$B$111:$Q$111,0)) -> 9.9 | G4: =INDEX($B$111:$Q$131,MATCH($B4,$B$111:$B$131,0),MATCH(G$2,$B$111:$Q$111,0)) -> 59.606917 | H4: =INDEX($B$111:$Q$131,MATCH($B4,$B$111:$B$131,0),MATCH(H$2,$B$111:$Q$111,0)) -> 0.41611229 | I4: =INDEX($B$111:$Q$131,MATCH($B4,$B$111:$B$131,0),MATCH(I$2,$B$111:$Q$111,0)) -> 16.798781 | J4: =IFERROR(K4/K18*100,) -> 30.395561 | K4: 10.304105 | L4: {=LOOKUP(1,0/($B$111:$B$131=$B4),$L$111:$L$131)} -> 10.304105 | M4: 0 | N4: =IF(P4>0,INDEX($B$111:$Z$131,MATCH(B4,$B$111:$B$131,0),MATCH($Z$111,$B$111:$Z$111,0))*C4*K4,C4*D4*K4) -> 2040.2128 | O4: =P4*K4 -> 173.93329 | P4: {=INDEX($B$111:$AF$131,MATCH($B4,$B$111:$B$131,0),COLUMN($AA$111)-1)} -> 16.88 | Q4: =SUM(N4:O4) -> 2214.1461 | S4: 原煤量 | T4: =$K$42 -> 25.030456 | U4: =W4 -> 25.030456 | V4: =W4 -> 25.030456 | W4: =$AP$230 -> 25.030456 | AA4: 内购煤 | AB4: =IFERROR(SUMPRODUCT($C$112:$C$115,$D$112:$D$115,$R$112:$R$115)/SUMPRODUCT($C$112:$C$115,$R$112:$R$115),) -> 0.12014458 | AC4: =IFERROR(SUMPRODUCT($C$112:$C$115,$R$112:$R$115)/SUM($R$112:$R$115),) -> 2220.5278 | AD4: =SUM($R$112:$R$115) -> 26.854121 | AE4: =AB4*AC4*AD4 -> 7164.2601
A5: =AP145 -> 42169.721 | B5: =$B$114 -> 州景 | C5: =INDEX($B$111:$Q$131,MATCH($B5,$B$111:$B$131,0),MATCH(C$2,$B$111:$Q$111,0)) -> 0 | D5: {=INDEX($B$111:$Q$131,MATCH($B5,$B$111:$B$131,0),COLUMN($D$2)-1)} -> 0 | E5: =C5*D5 -> 0 | F5: =INDEX($B$111:$Q$131,MATCH($B5,$B$111:$B$131,0),MATCH(F$2,$B$111:$Q$111,0)) -> 15.681 | G5: =INDEX($B$111:$Q$131,MATCH($B5,$B$111:$B$131,0),MATCH(G$2,$B$111:$Q$111,0)) -> 65.22 | H5: =INDEX($B$111:$Q$131,MATCH($B5,$B$111:$B$131,0),MATCH(H$2,$B$111:$Q$111,0)) -> 0.63 | I5: =INDEX($B$111:$Q$131,MATCH($B5,$B$111:$B$131,0),MATCH(I$2,$B$111:$Q$111,0)) -> 58.6 | J5: =IFERROR(K5/K18*100,) -> 0 | K5: 0 | L5: {=LOOKUP(1,0/($B$111:$B$131=$B5),$L$111:$L$131)} -> 0 | M5: 0 | N5: =IF(P5>0,INDEX($B$111:$Z$131,MATCH(B5,$B$111:$B$131,0),MATCH($Z$111,$B$111:$Z$111,0))*C5*K5,C5*D5*K5) -> 0 | O5: =P5*K5 -> 0 | P5: {=INDEX($B$111:$AF$131,MATCH($B5,$B$111:$B$131,0),COLUMN($AA$111)-1)} -> 12.88 | Q5: =SUM(N5:O5) -> 0 | S5: 原煤量 | T5: =$K$66 -> 0 | U5: =W5 -> 0 | V5: =W5 -> 0 | W5: =$AP$296 -> 0 | Z5: 百矿 | AA5: 外购煤 | AB5: =IFERROR(SUMPRODUCT($C$116:$C$130,$D$116:$D$130,$R$116:$R$130)/SUMPRODUCT($C$116:$C$130,$R$116:$R$130),) -> 0.16142174 | AC5: =IFERROR(SUMPRODUCT($C$116:$C$130,$R$116:$R$130)/SUM($R$116:$R$130),) -> 4600 | AD5: =SUM($R$116:$R$130) -> 7.0459113 | AE5: =AB5*AC5*AD5 -> 5231.871
A6: 综合厂用电率 | B6: =$B$115 -> 那荷 | C6: =INDEX($B$111:$Q$131,MATCH($B6,$B$111:$B$131,0),MATCH(C$2,$B$111:$Q$111,0)) -> 0 | D6: {=INDEX($B$111:$Q$131,MATCH($B6,$B$111:$B$131,0),COLUMN($D$2)-1)} -> 0 | E6: =C6*D6 -> 0 | F6: =INDEX($B$111:$Q$131,MATCH($B6,$B$111:$B$131,0),MATCH(F$2,$B$111:$Q$111,0)) -> 8.93 | G6: =INDEX($B$111:$Q$131,MATCH($B6,$B$111:$B$131,0),MATCH(G$2,$B$111:$Q$111,0)) -> 71.46 | H6: =INDEX($B$111:$Q$131,MATCH($B6,$B$111:$B$131,0),MATCH(H$2,$B$111:$Q$111,0)) -> 0.34 | I6: =INDEX($B$111:$Q$131,MATCH($B6,$B$111:$B$131,0),MATCH(I$2,$B$111:$Q$111,0)) -> 56.85 | J6: =IFERROR(K6/K18*100,) -> 0 | K6: 0 | L6: {=LOOKUP(1,0/($B$111:$B$131=$B6),$L$111:$L$131)} -> 0 | M6: 0 | N6: =IF(P6>0,INDEX($B$111:$Z$131,MATCH(B6,$B$111:$B$131,0),MATCH($Z$111,$B$111:$Z$111,0))*C6*K6,C6*D6*K6) -> 0 | O6: =P6*K6 -> 0 | P6: {=INDEX($B$111:$AF$131,MATCH($B6,$B$111:$B$131,0),COLUMN($AA$111)-1)} -> 8.43 | Q6: =SUM(N6:O6) -> 0 | S6: 原煤量 | T6: =$K$90 -> 0 | U6: =W6 -> 0 | V6: =W6 -> 0 | W6: =$AP$362 -> 0 | AA6: 合计 | AB6: =IFERROR(SUMPRODUCT($C$112:$C$130,$D$112:$D$130,$R$112:$R$130)/SUMPRODUCT($C$112:$C$130,$R$112:$R$130),) -> 0.13467978 | AC6: =IFERROR(SUMPRODUCT($C$112:$C$130,$R$112:$R$130)/SUMPRODUCT($R$112:$R$130),) -> 2715.0863 | AD6: =SUM($R$112:$R$130) -> 33.900032 | AE6: =AB6*AC6*AD6 -> 12396.131
A7: 6.0952299 | B7: =$B$116 -> 褐煤2（云）长协 | C7: =INDEX($B$111:$Q$131,MATCH($B7,$B$111:$B$131,0),MATCH(C$2,$B$111:$Q$111,0)) -> 2400 | D7: {=INDEX($B$111:$Q$131,MATCH($B7,$B$111:$B$131,0),COLUMN($D$2)-1)} -> 0.123 | E7: =C7*D7 -> 295.2 | F7: =INDEX($B$111:$Q$131,MATCH($B7,$B$111:$B$131,0),MATCH(F$2,$B$111:$Q$111,0)) -> 19.2 | G7: =INDEX($B$111:$Q$131,MATCH($B7,$B$111:$B$131,0),MATCH(G$2,$B$111:$Q$111,0)) -> 32.974564 | H7: =INDEX($B$111:$Q$131,MATCH($B7,$B$111:$B$131,0),MATCH(H$2,$B$111:$Q$111,0)) -> 0.80500871 | I7: =INDEX($B$111:$Q$131,MATCH($B7,$B$111:$B$131,0),MATCH(I$2,$B$111:$Q$111,0)) -> 28.483232 | J7: =IFERROR(K7/K18*100,) -> 0 | K7: 0 | L7: 0 | M7: 0 | N7: =IF(P7>0,INDEX($B$111:$Z$131,MATCH(B7,$B$111:$B$131,0),MATCH($Z$111,$B$111:$Z$111,0))*C7*K7,C7*D7*K7) -> 0 | O7: =P7*K7 -> 0 | P7: {=INDEX($B$111:$AF$131,MATCH($B7,$B$111:$B$131,0),COLUMN($AA$111)-1)} -> 0 | Q7: =SUM(N7:O7) -> 0 | S7: 配煤热值 | T7: =$C$18 -> 2715.0863 | U7: 4100 | V7: 2629 | AA7: 内购煤 | AB7: =IFERROR(SUMPRODUCT($C$112:$C$115,$D$112:$D$115,$S$112:$S$115)/SUMPRODUCT($C$112:$C$115,$S$112:$S$115),) -> 0 | AC7: =IFERROR(SUMPRODUCT($C$112:$C$115,$S$112:$S$115)/SUM($S$112:$S$115),) -> 0 | AD7: =SUM($S$112:$S$115) -> 0 | AE7: =AB7*AC7*AD7 -> 0
A8: 发电标煤耗 | B8: =$B$117 -> 褐煤3（云）长协 | C8: =INDEX($B$111:$Q$131,MATCH($B8,$B$111:$B$131,0),MATCH(C$2,$B$111:$Q$111,0)) -> 3200 | D8: {=INDEX($B$111:$Q$131,MATCH($B8,$B$111:$B$131,0),COLUMN($D$2)-1)} -> 0.133 | E8: =C8*D8 -> 425.6 | F8: =INDEX($B$111:$Q$131,MATCH($B8,$B$111:$B$131,0),MATCH(F$2,$B$111:$Q$111,0)) -> 19.15 | G8: =INDEX($B$111:$Q$131,MATCH($B8,$B$111:$B$131,0),MATCH(G$2,$B$111:$Q$111,0)) -> 23.873821 | H8: =INDEX($B$111:$Q$131,MATCH($B8,$B$111:$B$131,0),MATCH(H$2,$B$111:$Q$111,0)) -> 0.84706369 | I8: =INDEX($B$111:$Q$131,MATCH($B8,$B$111:$B$131,0),MATCH(I$2,$B$111:$Q$111,0)) -> 30.507667 | J8: =IFERROR(K8/K18*100,) -> 0 | K8: 0 | L8: 0 | M8: 0 | N8: =IF(P8>0,INDEX($B$111:$Z$131,MATCH(B8,$B$111:$B$131,0),MATCH($Z$111,$B$111:$Z$111,0))*C8*K8,C8*D8*K8) -> 0 | O8: =P8*K8 -> 0 | P8: {=INDEX($B$111:$AF$131,MATCH($B8,$B$111:$B$131,0),COLUMN($AA$111)-1)} -> 0 | Q8: =SUM(N8:O8) -> 0 | S8: 配煤热值 | T8: =$C$42 -> 3193.7132 | U8: 3943.47 | V8: 2600 | Z8: 德保 | AA8: 外购煤 | AB8: =IFERROR(SUMPRODUCT($C$116:$C$130,$E$116:$E$130,$S$116:$S$130)/SUMPRODUCT($C$116:$C$130,$S$116:$S$130),) -> 0.13893587 | AC8: =IFERROR(SUMPRODUCT($C$116:$C$130,$S$116:$S$130)/SUM($S$116:$S$130),) -> 3193.7132 | AD8: =SUM($S$116:$S$130) -> 25.030456 | AE8: =AB8*AC8*AD8 -> 11106.547
A9: =AP138 -> 311.80637 | B9: =$B$118 -> 褐煤3（云） | C9: =INDEX($B$111:$Q$131,MATCH($B9,$B$111:$B$131,0),MATCH(C$2,$B$111:$Q$111,0)) -> 3200 | D9: {=INDEX($B$111:$Q$131,MATCH($B9,$B$111:$B$131,0),COLUMN($D$2)-1)} -> 0.1333 | E9: =C9*D9 -> 426.56 | F9: =INDEX($B$111:$Q$131,MATCH($B9,$B$111:$B$131,0),MATCH(F$2,$B$111:$Q$111,0)) -> 19.15 | G9: =INDEX($B$111:$Q$131,MATCH($B9,$B$111:$B$131,0),MATCH(G$2,$B$111:$Q$111,0)) -> 23.873821 | H9: =INDEX($B$111:$Q$131,MATCH($B9,$B$111:$B$131,0),MATCH(H$2,$B$111:$Q$111,0)) -> 0.84706369 | I9: =INDEX($B$111:$Q$131,MATCH($B9,$B$111:$B$131,0),MATCH(I$2,$B$111:$Q$111,0)) -> 30.507667 | J9: =IFERROR(K9/K18*100,) -> 0 | K9: 0 | L9: 0 | M9: 0 | N9: =IF(P9>0,INDEX($B$111:$Z$131,MATCH(B9,$B$111:$B$131,0),MATCH($Z$111,$B$111:$Z$111,0))*C9*K9,C9*D9*K9) -> 0 | O9: =P9*K9 -> 0 | P9: {=INDEX($B$111:$AF$131,MATCH($B9,$B$111:$B$131,0),COLUMN($AA$111)-1)} -> 0 | Q9: =SUM(N9:O9) -> 0 | S9: 配煤热值 | T9: =$C$66 -> 0 | U9: 3756.9351 | V9: 0 | AA9: 合计 | AB9: =IFERROR(SUMPRODUCT($C$112:$C$130,$E$112:$E$130,$S$112:$S$130)/SUMPRODUCT($C$112:$C$130,$S$112:$S$130),) -> 0.13893587 | AC9: =IFERROR(SUMPRODUCT($C$112:$C$130,$S$112:$S$130)/SUMPRODUCT($S$112:$S$130),) -> 3193.7132 | AD9: =SUM($S$112:$S$130) -> 25.030456 | AE9: =AB9*AC9*AD9 -> 11106.547
A10: 自产比例（%） | B10: =$B$119 -> 褐煤32（港1） | C10: =INDEX($B$111:$Q$131,MATCH($B10,$B$111:$B$131,0),MATCH(C$2,$B$111:$Q$111,0)) -> 3200 | D10: {=INDEX($B$111:$Q$131,MATCH($B10,$B$111:$B$131,0),COLUMN($D$2)-1)} -> 0.1687875 | E10: =C10*D10 -> 540.12 | F10: =INDEX($B$111:$Q$131,MATCH($B10,$B$111:$B$131,0),MATCH(F$2,$B$111:$Q$111,0)) -> 32.112709 | G10: =INDEX($B$111:$Q$131,MATCH($B10,$B$111:$B$131,0),MATCH(G$2,$B$111:$Q$111,0)) -> 19.443643 | H10: =INDEX($B$111:$Q$131,MATCH($B10,$B$111:$B$131,0),MATCH(H$2,$B$111:$Q$111,0)) -> 0.77574029 | I10: =INDEX($B$111:$Q$131,MATCH($B10,$B$111:$B$131,0),MATCH(I$2,$B$111:$Q$111,0)) -> 24.82919 | J10: =IFERROR(K10/K18*100,) -> 0 | K10: 0 | L10: 0 | M10: 0 | N10: =IF(P10>0,INDEX($B$111:$Z$131,MATCH(B10,$B$111:$B$131,0),MATCH($Z$111,$B$111:$Z$111,0))*C10*K10,C10*D10*K10) -> 0 | O10: =P10*K10 -> 0 | P10: {=INDEX($B$111:$AF$131,MATCH($B10,$B$111:$B$131,0),COLUMN($AA$111)-1)} -> 95.32 | Q10: =SUM(N10:O10) -> 0 | S10: 配煤热值 | T10: =$C$90 -> 0 | U10: 3756.9351 | V10: 0 | AA10: 内购煤 | AB10: =IFERROR(SUMPRODUCT($C$112:$C$115,$D$112:$D$115,$T$112:$T$115)/SUMPRODUCT($C$112:$C$115,$T$112:$T$115),) -> 0 | AC10: =IFERROR(SUMPRODUCT($C$112:$C$115,$T$112:$T$115)/SUM($T$112:$T$115),) -> 0 | AD10: =SUM($T$112:$T$115) -> 0 | AE10: =AB10*AC10*AD10 -> 0
A11: =(SUMIF($B$3:$B$17,$B$112,$K$3:$K$17)+SUMIF($B$3:$B$17,$B$113,$K$3:$K$17)+SUMIF($B$3:$B$17,$B$114,$K$3:$K$17)+SUMIF($B$3:$B$17,$B$115,$K$3:$K$17))/$K$18*100 -> 79.215621 | B11: =$B$120 -> 褐煤35（港2） | C11: =INDEX($B$111:$Q$131,MATCH($B11,$B$111:$B$131,0),MATCH(C$2,$B$111:$Q$111,0)) -> 3500 | D11: {=INDEX($B$111:$Q$131,MATCH($B11,$B$111:$B$131,0),COLUMN($D$2)-1)} -> 0.17313429 | E11: =C11*D11 -> 605.97 | F11: =INDEX($B$111:$Q$131,MATCH($B11,$B$111:$B$131,0),MATCH(F$2,$B$111:$Q$111,0)) -> 29.814059 | G11: =INDEX($B$111:$Q$131,MATCH($B11,$B$111:$B$131,0),MATCH(G$2,$B$111:$Q$111,0)) -> 17.717186 | H11: =INDEX($B$111:$Q$131,MATCH($B11,$B$111:$B$131,0),MATCH(H$2,$B$111:$Q$111,0)) -> 0.78167601 | I11: =INDEX($B$111:$Q$131,MATCH($B11,$B$111:$B$131,0),MATCH(I$2,$B$111:$Q$111,0)) -> 26.875931 | J11: =IFERROR(K11/K18*100,) -> 0 | K11: 0 | L11: 0 | M11: 0 | N11: =IF(P11>0,INDEX($B$111:$Z$131,MATCH(B11,$B$111:$B$131,0),MATCH($Z$111,$B$111:$Z$111,0))*C11*K11,C11*D11*K11) -> 0 | O11: =P11*K11 -> 0 | P11: {=INDEX($B$111:$AF$131,MATCH($B11,$B$111:$B$131,0),COLUMN($AA$111)-1)} -> 95.32 | Q11: =SUM(N11:O11) -> 0 | S11: 入炉硫量（t/h） | T11: =IFERROR($T$3/SUM($AQ$146,$AR$146)*10000*$H$18/100,) -> 2.5514304 | U11: 4.03 | V11: 0 | Z11: 银海 | AA11: 外购煤 | AB11: =IFERROR(SUMPRODUCT($C$116:$C$130,$D$116:$D$130,$T$116:$T$130)/SUMPRODUCT($C$116:$C$130,$T$116:$T$130),) -> 0 | AC11: =IFERROR(SUMPRODUCT($C$116:$C$130,$T$116:$T$130)/SUM($T$116:$T$130),) -> 0 | AD11: =SUM($T$116:$T$130) -> 0 | AE11: =AB11*AC11*AD11 -> 0
A12: 利润（万元） | B12: =$B$121 -> 褐煤38（港3） | C12: =INDEX($B$111:$Q$131,MATCH($B12,$B$111:$B$131,0),MATCH(C$2,$B$111:$Q$111,0)) -> 3800 | D12: {=INDEX($B$111:$Q$131,MATCH($B12,$B$111:$B$131,0),COLUMN($D$2)-1)} -> 0.16938421 | E12: =C12*D12 -> 643.66 | F12: =INDEX($B$111:$Q$131,MATCH($B12,$B$111:$B$131,0),MATCH(F$2,$B$111:$Q$111,0)) -> 34.679691 | G12: =INDEX($B$111:$Q$131,MATCH($B12,$B$111:$B$131,0),MATCH(G$2,$B$111:$Q$111,0)) -> 8.6727633 | H12: =INDEX($B$111:$Q$131,MATCH($B12,$B$111:$B$131,0),MATCH(H$2,$B$111:$Q$111,0)) -> 0.82970573 | I12: =INDEX($B$111:$Q$131,MATCH($B12,$B$111:$B$131,0),MATCH(I$2,$B$111:$Q$111,0)) -> 28.638706 | J12: =IFERROR(K12/K18*100,) -> 0 | K12: 0 | L12: 0 | M12: 0 | N12: =IF(P12>0,INDEX($B$111:$Z$131,MATCH(B12,$B$111:$B$131,0),MATCH($Z$111,$B$111:$Z$111,0))*C12*K12,C12*D12*K12) -> 0 | O12: =P12*K12 -> 0 | P12: {=INDEX($B$111:$AF$131,MATCH($B12,$B$111:$B$131,0),COLUMN($AA$111)-1)} -> 95.32 | Q12: =SUM(N12:O12) -> 0 | S12: 入炉硫量（t/h） | T12: =IFERROR($T$4/SUM($AQ$212:$AR$212)*10000*$H$42/100,) -> 1.7469984 | U12: 5.06 | V12: 0 | AA12: 合计 | AB12: =IFERROR(SUMPRODUCT($C$112:$C$130,$D$112:$D$130,$T$112:$T$130)/SUMPRODUCT($C$112:$C$130,$T$112:$T$130),) -> 0 | AC12: =IFERROR(SUMPRODUCT($C$112:$C$130,$T$112:$T$130)/SUMPRODUCT($T$112:$T$130),) -> 0 | AD12: =SUM($T$112:$T$130) -> 0 | AE12: =AB12*AC12*AD12 -> 0
A13: =C105 -> 5540.3192 | B13: =$B$122 -> 褐煤46 | C13: =INDEX($B$111:$Q$131,MATCH($B13,$B$111:$B$131,0),MATCH(C$2,$B$111:$Q$111,0)) -> 4600 | D13: {=INDEX($B$111:$Q$131,MATCH($B13,$B$111:$B$131,0),COLUMN($D$2)-1)} -> 0.16142174 | E13: =C13*D13 -> 742.54 | F13: =INDEX($B$111:$Q$131,MATCH($B13,$B$111:$B$131,0),MATCH(F$2,$B$111:$Q$111,0)) -> 23.091665 | G13: =INDEX($B$111:$Q$131,MATCH($B13,$B$111:$B$131,0),MATCH(G$2,$B$111:$Q$111,0)) -> 10.878752 | H13: =INDEX($B$111:$Q$131,MATCH($B13,$B$111:$B$131,0),MATCH(H$2,$B$111:$Q$111,0)) -> 0.20812534 | I13: =INDEX($B$111:$Q$131,MATCH($B13,$B$111:$B$131,0),MATCH(I$2,$B$111:$Q$111,0)) -> 32.849465 | J13: =IFERROR(K13/K18*100,) -> 20.784379 | K13: 7.0459113 | L13: {=LOOKUP(1,0/($B$111:$B$131=$B13),$L$111:$L$131)} -> 100 | M13: 0 | N13: =IF(P13>0,INDEX($B$111:$Z$131,MATCH(B13,$B$111:$B$131,0),MATCH($Z$111,$B$111:$Z$111,0))*C13*K13,C13*D13*K13) -> 4560.2547 | O13: =P13*K13 -> 671.61627 | P13: {=INDEX($B$111:$AF$131,MATCH($B13,$B$111:$B$131,0),COLUMN($AA$111)-1)} -> 95.32 | Q13: =SUM(N13:O13) -> 5231.871 | S13: 入炉硫量（t/h） | T13: =IFERROR($T$5/SUM($AQ$278:$AR$278)*10000*$H$66/100,) -> 0 | U13: 3 | V13: 0 | AA13: 内购煤 | AB13: =IFERROR(SUMPRODUCT($C$112:$C$115,$F$112:$F$115,$U$112:$U$115)/SUMPRODUCT($C$112:$C$115,$U$112:$U$115),) -> 0 | AC13: =IFERROR(SUMPRODUCT($C$112:$C$115,$U$112:$U$115)/SUM($U$112:$U$115),) -> 0 | AD13: =SUM($U$112:$U$115) -> 0 | AE13: =AB13*AC13*AD13 -> 0
A14: 锅炉效率（%） | B14: =$B$123 -> 烟煤55 | C14: =INDEX($B$111:$Q$131,MATCH($B14,$B$111:$B$131,0),MATCH(C$2,$B$111:$Q$111,0)) -> 5500 | D14: {=INDEX($B$111:$Q$131,MATCH($B14,$B$111:$B$131,0),COLUMN($D$2)-1)} -> 0.16633091 | E14: =C14*D14 -> 914.82 | F14: =INDEX($B$111:$Q$131,MATCH($B14,$B$111:$B$131,0),MATCH(F$2,$B$111:$Q$111,0)) -> 10.316451 | G14: =INDEX($B$111:$Q$131,MATCH($B14,$B$111:$B$131,0),MATCH(G$2,$B$111:$Q$111,0)) -> 19.875802 | H14: =INDEX($B$111:$Q$131,MATCH($B14,$B$111:$B$131,0),MATCH(H$2,$B$111:$Q$111,0)) -> 0.47663777 | I14: =INDEX($B$111:$Q$131,MATCH($B14,$B$111:$B$131,0),MATCH(I$2,$B$111:$Q$111,0)) -> 25.313893 | J14: =IFERROR(K14/K18*100,) -> 0 | K14: 0 | L14: {=LOOKUP(1,0/($B$111:$B$131=$B14),$L$111:$L$131)} -> 100 | M14: 0 | N14: =IF(P14>0,INDEX($B$111:$Z$131,MATCH(B14,$B$111:$B$131,0),MATCH($Z$111,$B$111:$Z$111,0))*C14*K14,C14*D14*K14) -> 0 | O14: =P14*K14 -> 0 | P14: {=INDEX($B$111:$AF$131,MATCH($B14,$B$111:$B$131,0),COLUMN($AA$111)-1)} -> 95.32 | Q14: =SUM(N14:O14) -> 0 | S14: 入炉硫量（t/h） | T14: =IFERROR($T$6/SUM($AQ$344:$AR$344)*10000*$H$90/100,) -> 0 | U14: 0.9 | V14: 0 | Z14: 田东 | AA14: 外购煤 | AB14: =IFERROR(SUMPRODUCT($C$116:$C$130,$F$116:$F$130,$U$116:$U$130)/SUMPRODUCT($C$116:$C$130,$U$116:$U$130),) -> 0 | AC14: =IFERROR(SUMPRODUCT($C$116:$C$130,$U$116:$U$130)/SUM($U$116:$U$130),) -> 0 | AD14: =SUM($U$116:$U$130) -> 0 | AE14: =AB14*AC14*AD14 -> 0
A15: =AP139*100 -> 88.88407 | B15: =$B$124 -> 烟煤50备 | C15: =INDEX($B$111:$Q$131,MATCH($B15,$B$111:$B$131,0),MATCH(C$2,$B$111:$Q$111,0)) -> 5000 | D15: {=INDEX($B$111:$Q$131,MATCH($B15,$B$111:$B$131,0),COLUMN($D$2)-1)} -> 0 | E15: =C15*D15 -> 0 | F15: =INDEX($B$111:$Q$131,MATCH($B15,$B$111:$B$131,0),MATCH(F$2,$B$111:$Q$111,0)) -> 0 | G15: =INDEX($B$111:$Q$131,MATCH($B15,$B$111:$B$131,0),MATCH(G$2,$B$111:$Q$111,0)) -> 0 | H15: =INDEX($B$111:$Q$131,MATCH($B15,$B$111:$B$131,0),MATCH(H$2,$B$111:$Q$111,0)) -> 0 | I15: =INDEX($B$111:$Q$131,MATCH($B15,$B$111:$B$131,0),MATCH(I$2,$B$111:$Q$111,0)) -> 0 | J15: =IFERROR(K15/K18*100,) -> 0 | K15: 0 | L15: {=LOOKUP(1,0/($B$111:$B$131=$B15),$L$111:$L$131)} -> 0 | M15: 0 | N15: =IF(P15>0,INDEX($B$111:$Z$131,MATCH(B15,$B$111:$B$131,0),MATCH($Z$111,$B$111:$Z$111,0))*C15*K15,C15*D15*K15) -> 0 | O15: =P15*K15 -> 0 | P15: {=INDEX($B$111:$AF$131,MATCH($B15,$B$111:$B$131,0),COLUMN($AA$111)-1)} -> 0 | Q15: =SUM(N15:O15) -> 0 | S15: 矸石退税 | T15: =IFERROR(((SUMIF($B$3:$B$17,$B$112,$K$3:$K$17)+SUMIF($B$3:$B$17,$B$113,$K$3:$K$17)+SUMIF($B$3:$B$17,$B$114,$K$3:$K$17)+SUMIF($B$3:$B$17,$B$115,$K$3:$K$17))*(1-13%)+SUMIF($B$3:$B$17,$B$116,$K$3:$K$17)+SUMIF($B$3:$B$17,$B$117,$K$3:$K$17))/$K$18*100,) -> 68.91759 | U15: 100 | V15: 60 | AA15: 合计 | AB15: =IFERROR(SUMPRODUCT($C$112:$C$130,$F$112:$F$130,$U$112:$U$130)/SUMPRODUCT($C$112:$C$130,$U$112:$U$130),) -> 0 | AC15: =IFERROR(SUMPRODUCT($C$112:$C$130,$U$112:$U$130)/SUMPRODUCT($U$112:$U$130),) -> 0 | AD15: =SUM($U$112:$U$130) -> 0 | AE15: =AB15*AC15*AD15 -> 0
A16: 汽机热耗率 | B16: =$B$125 -> 烟煤55备 | C16: =INDEX($B$111:$Q$131,MATCH($B16,$B$111:$B$131,0),MATCH(C$2,$B$111:$Q$111,0)) -> 5500 | D16: {=INDEX($B$111:$Q$131,MATCH($B16,$B$111:$B$131,0),COLUMN($D$2)-1)} -> 0 | E16: =C16*D16 -> 0 | F16: =INDEX($B$111:$Q$131,MATCH($B16,$B$111:$B$131,0),MATCH(F$2,$B$111:$Q$111,0)) -> 0 | G16: =INDEX($B$111:$Q$131,MATCH($B16,$B$111:$B$131,0),MATCH(G$2,$B$111:$Q$111,0)) -> 0 | H16: =INDEX($B$111:$Q$131,MATCH($B16,$B$111:$B$131,0),MATCH(H$2,$B$111:$Q$111,0)) -> 0 | I16: =INDEX($B$111:$Q$131,MATCH($B16,$B$111:$B$131,0),MATCH(I$2,$B$111:$Q$111,0)) -> 0 | J16: =IFERROR(K16/K18*100,) -> 0 | K16: 0 | L16: {=LOOKUP(1,0/($B$111:$B$131=$B16),$L$111:$L$131)} -> 0 | M16: 0 | N16: =IF(P16>0,INDEX($B$111:$Z$131,MATCH(B16,$B$111:$B$131,0),MATCH($Z$111,$B$111:$Z$111,0))*C16*K16,C16*D16*K16) -> 0 | O16: =P16*K16 -> 0 | P16: {=INDEX($B$111:$AF$131,MATCH($B16,$B$111:$B$131,0),COLUMN($AA$111)-1)} -> 0 | Q16: =SUM(N16:O16) -> 0 | S16: 矸石退税 | T16: =IFERROR(((SUMIF($B$27:$B$41,$B$112,$K$27:$K$41)+SUMIF($B$27:$B$41,$B$113,$K$27:$K$41)+SUMIF($B$27:$B$41,$B$114,$K$27:$K$41)+SUMIF($B$27:$B$41,$B$115,$K$27:$K$41))*(1-13%)+SUMIF($B$27:$B$41,$B$116,$K$27:$K$41)+SUMIF($B$27:$B$41,$B$117,$K$27:$K$41))/$K$42*100,) -> 47.941596 | U16: 100 | V16: 0 | AA16: 内购煤 | AB16: =(AB4*AC4*AD4+AB7*AC7*AD7+AB10*AC10*AD10+AB13*AC13*AD13)/(AC4*AD4+AC7*AD7+AC10*AD10+AC13*AD13) -> 0.12014458 | AC16: =(AC4*AD4+AC7*AD7+AC10*AD10+AC13*AD13)/(AD4+AD7+AD10+AD13) -> 2220.5278 | AD16: =SUM($K$112:$K$115) -> 26.854121 | AE16: =AB16*AC16*AD16 -> 7164.2601
A17: =AP140 -> 8025.02 | B17: =$B$127 -> 石油焦 | C17: =INDEX($B$111:$Q$131,MATCH($B17,$B$111:$B$131,0),MATCH(C$2,$B$111:$Q$111,0)) -> 7256.4478 | D17: {=INDEX($B$111:$Q$131,MATCH($B17,$B$111:$B$131,0),COLUMN($D$2)-1)} -> 0 | E17: =C17*D17 -> 0 | F17: =INDEX($B$111:$Q$131,MATCH($B17,$B$111:$B$131,0),MATCH(F$2,$B$111:$Q$111,0)) -> 0 | G17: =INDEX($B$111:$Q$131,MATCH($B17,$B$111:$B$131,0),MATCH(G$2,$B$111:$Q$111,0)) -> 0 | H17: =INDEX($B$111:$Q$131,MATCH($B17,$B$111:$B$131,0),MATCH(H$2,$B$111:$Q$111,0)) -> 0 | I17: =INDEX($B$111:$Q$131,MATCH($B17,$B$111:$B$131,0),MATCH(I$2,$B$111:$Q$111,0)) -> 0 | J17: =IFERROR(K17/K18*100,) -> 0 | K17: 0 | L17: {=LOOKUP(1,0/($B$111:$B$131=$B17),$L$111:$L$131)} -> 0 | M17: 0 | N17: =IF(P17>0,INDEX($B$111:$Z$131,MATCH(B17,$B$111:$B$131,0),MATCH($Z$111,$B$111:$Z$111,0))*C17*K17,C17*D17*K17) -> 0 | O17: =P17*K17 -> 0 | P17: {=INDEX($B$111:$AF$131,MATCH($B17,$B$111:$B$131,0),COLUMN($AA$111)-1)} -> 0 | Q17: =SUM(N17:O17) -> 0 | S17: 矸石退税 | T17: =IFERROR(((SUMIF($B$51:$B$65,$B$112,$K$51:$K$65)+SUMIF($B$51:$B$65,$B$113,$K$51:$K$65)+SUMIF($B$51:$B$65,$B$114,$K$51:$K$65)+SUMIF($B$51:$B$65,$B$115,$K$51:$K$65))*(1-13%)+SUMIF($B$51:$B$65,$B$116,$K$51:$K$65)+SUMIF($B$51:$B$65,$B$117,$K$51:$K$65))/$K$66*100,) -> 0 | U17: 100 | V17: 0 | Z17: 业务部 | AA17: 外购煤 | AB17: =(AB5*AC5*AD5+AB8*AC8*AD8+AB11*AC11*AD11+AB14*AC14*AD14)/(AC5*AD5+AC8*AD8+AC11*AD11+AC14*AD14) -> 0.14542261 | AC17: =(AC5*AD5+AC8*AD8+AC11*AD11+AC14*AD14)/(AD5+AD8+AD11+AD14) -> 3502.6189 | AD17: =SUM($K$116:$K$130) -> 32.076367 | AE17: =AB17*AC17*AD17 -> 16338.418
B18: 加权平均 | C18: =IFERROR(SUMPRODUCT(C3:C17,K3:K17)/SUM(K3:K17),) -> 2715.0863 | D18: =IFERROR(SUMPRODUCT(C3:C17,D3:D17,K3:K17)/SUMPRODUCT(C3:C17,K3:K17),) -> 0.13467978 | E18: =IFERROR(SUMPRODUCT(C3:C17,E3:E17,K3:K17)/SUMPRODUCT(C3:C17,K3:K17),) -> 438.28033 | F18: =IFERROR(SUMPRODUCT(F3:F17,K3:K17)/SUM(K3:K17),) -> 12.226835 | G18: =IFERROR(SUMPRODUCT(G3:G17,K3:K17)/SUM(K3:K17),) -> 46.62139 | H18: =IFERROR(SUMPRODUCT(H3:H17,K3:K17)/SUM(K3:K17),) -> 0.92122355 | I18: =IFERROR(SUMPRODUCT(I3:I17,K3:K17)/SUM(K3:K17),) -> 21.815228 | J18: =IFERROR(SUM(J3:J17),) -> 100 | K18: =IFERROR(SUM(K3:K17),) -> 33.900032 | L18: =SUM(L3:L17) -> 226.85412 | M18: =SUM(M3:M17) -> 0 | N18: =SUM(N3:N17) -> 11325.005 | O18: =SUM(O3:O17) -> 1071.1263 | P18: =IFERROR(SUMPRODUCT(P3:P17,K3:K17)/SUM(K3:K17),) -> 31.596615 | Q18: =SUM(Q3:Q17) -> 12396.131 | R18: =SUM(R3:R17) -> 0 | S18: 矸石退税 | T18: =IFERROR(((SUMIF($B$75:$B$89,$B$112,$K$75:$K$89)+SUMIF($B$75:$B$89,$B$113,$K$75:$K$89)+SUMIF($B$75:$B$89,$B$114,$K$75:$K$89)+SUMIF($B$75:$B$89,$B$115,$K$75:$K$89))*(1-13%)+SUMIF($B$75:$B$89,$B$116,$K$75:$K$89)+SUMIF($B$75:$B$89,$B$117,$K$75:$K$89))/$K$90*100,) -> 0 | U18: 100 | V18: 0 | AA18: 合计 | AB18: =(AB6*AC6*AD6+AB9*AC9*AD9+AB12*AC12*AD12+AB15*AC15*AD15)/(AC6*AD6+AC9*AD9+AC12*AD12+AC15*AD15) -> 0.13665809 | AC18: =(AC6*AD6+AC9*AD9+AC12*AD12+AC15*AD15)/(AD6+AD9+AD12+AD15) -> 2918.3809 | AD18: =SUM($K$112:$K$130) -> 58.930488 | AE18: =AB18*AC18*AD18 -> 23502.678
B19: 炉灰占比% | C19: =T$47 -> 40 | D19: 炉灰产量（万吨） | E19: =$K18*$G18/100*C19/100 -> 6.3218665 | F19: 炉灰销售% | G19: =T$51 -> 40 | H19: 炉灰销量（万吨） | I19: =E19*G19/100 -> 2.5287466 | J19: 炉灰价格（元/吨） | K19: =T$54 -> -20 | L19: 炉灰收入（万元） | M19: =I19*K19 -> -50.574932 | N19: 炉灰税率% | O19: 13 | P19: 税后金额（万元） | Q19: =M19/(1+O19/100) -> -44.756577 | S19: 入炉煤量（t/h） | T19: =IFERROR($T$3/SUM($AQ$146,$AR$146)*10000,) -> 276.96105 | U19: 300 | V19: 0
B20: 炉渣占比% | C20: =100-C19 -> 60 | D20: 炉渣产量（万吨） | E20: =$K18*$G18/100*C20/100 -> 9.4827998 | F20: 炉渣销售% | G20: =T$52 -> 45 | H20: 炉渣销量（万吨） | I20: =E20*G20/100 -> 4.2672599 | J20: 炉渣价格（元/吨） | K20: =T$55 -> -8 | L20: 炉渣收入（万元） | M20: =I20*K20 -> -34.138079 | N20: 炉渣税率% | O20: 13 | P20: 税后金额（万元） | Q20: =M20/(1+O20/100) -> -30.21069 | S20: 入炉煤量（t/h） | T20: =IFERROR($T$4/SUM($AQ$212:$AR$212)*10000,) -> 248.31801 | U20: 300 | V20: 0 | Z20: 项目 | AA20: 单位 | AB20: 百矿 | AC20: 德保 | AD20: 银海 | AE20: 田东 | AF20: 合计
B21: 钙硫比 | C21: =T$49 -> 4.35 | D21: 石膏产量（万吨） | E21: =C22*I25 -> 2.649043 | F21: 石膏销售% | G21: =T$53 -> 38 | H21: 石膏销量（万吨） | I21: =E21*G21/100 -> 1.0066363 | J21: 石膏价格（元/吨） | K21: =T$56 -> -5 | L21: 石膏收入（万元） | M21: =I21*K21 -> -5.0331817 | N21: 硫酸铵税率% | O21: 13 | P21: 税后金额（万元） | Q21: =M21/(1+O21/100) -> -4.4541431 | S21: 入炉煤量（t/h） | T21: =IFERROR($T$5/SUM($AQ$278:$AR$278)*10000,) -> 0 | U21: 150 | V21: 0 | Z21: 炉灰产量 | AA21: 万吨 | AB21: =E19 -> 6.3218665 | AC21: =E43 -> 5.5269738 | AD21: =E67 -> 0 | AE21: =E91 -> 0 | AF21: =SUM(AB21:AE21) -> 11.84884
B22: 石膏石粉比 | C22: =T$50 -> 1.95 | D22: 销售蒸汽（万吨） | E22: =T$62 -> 0 | F22: 炉灰调湿比例% | G22: =T64 -> 25 | H22: 炉灰倒运量（万吨） | I22: =(E19-I19)/(1-G22/100) -> 5.0574932 | J22: 炉灰倒运单价（元/吨） | K22: =T$57 -> 7.9 | L22: 炉灰倒运费（万元） | M22: =I22*K22 -> 39.954197 | N22: 炉灰倒运税率% | O22: 6 | P22: 税后金额（万元） | Q22: =M22/(1+O22/100) -> 37.692638 | S22: 入炉煤量（t/h） | T22: =IFERROR($T$6/SUM($AQ$344:$AR$344)*10000,) -> 0 | U22: 150 | V22: 0 | Z22: 炉渣产量 | AA22: 万吨 | AB22: =E20 -> 9.4827998 | AC22: =E44 -> 0.6141082 | AD22: =E68 -> 0 | AE22: =E92 -> 0 | AF22: =SUM(AB22:AE22) -> 10.096908
D23: 蒸汽单价（元/吨） | E23: =T$63 -> 168 | F23: 炉渣调湿比例% | G23: =T65 -> 25 | H23: 炉渣倒运量（万吨） | I23: =(E20-I20)/(1-G23/100) -> 6.9540532 | J23: 炉渣倒运单价（元/吨） | K23: =T$58 -> 7.9 | L23: 炉渣倒运费（万元） | M23: =I23*K23 -> 54.93702 | N23: 炉渣倒运税率% | O23: 6 | P23: 税后金额（万元） | Q23: =M23/(1+O23/100) -> 51.827378 | S23: 灰渣总量（t/h） | T23: =IFERROR($T$3/SUM($AQ$146,$AR$146)*10000*$G$18/100,) -> 129.12309 | U23: 150 | V23: 0 | Z23: 石膏产量 | AA23: 万吨 | AB23: =E21 -> 2.649043 | AC23: =E45 -> 0.48809617 | AD23: =E69 -> 0 | AF23: =SUM(AB23:AE23) -> 3.1371392
D24: 蒸汽收入（万元） | E24: =E22*E23 -> 0 | H24: 石膏倒运量（万吨） | I24: =E21-I21 -> 1.6424067 | J24: 石膏倒运单价（元/吨） | K24: =T$59 -> 7.9 | L24: 石膏倒运费（万元） | M24: =I24*K24 -> 12.975013 | N24: 石膏运税率% | O24: 6 | P24: 税后金额（万元） | Q24: =M24/(1+O24/100) -> 12.240578 | S24: 灰渣总量（t/h） | T24: =IFERROR($T$4/SUM($AQ$212:$AR$212)*10000*$G$42/100,) -> 60.923432 | U24: 104.57 | V24: 0 | Z24: 硫酸铵产量 | AA24: 万吨 | AE24: =E93 -> 0 | AF24: =SUM(AB24:AE24) -> 0
D25: 税率% | E25: 9 | H25: 石粉耗用（万吨） | I25: =H18/100*K18*C21 -> 1.3584836 | J25: 石粉单价（元/吨） | K25: =T$60 -> 67 | L25: 石粉费用（万元） | M25: =I25*K25 -> 91.018401 | N25: 石粉税率% | O25: 13 | P25: 税后金额（万元） | Q25: =M25/(1+O25/100) -> 80.547258 | S25: 灰渣总量（t/h） | T25: =IFERROR($T$5/SUM($AQ$278:$AR$278)*10000*$G$66/100,) -> 0 | U25: 43.88 | V25: 0 | Z25: 炉灰销量 | AA25: 万吨 | AB25: =I19 -> 2.5287466 | AC25: =I43 -> 1.4253188 | AD25: =I67 -> 0 | AE25: =I91 -> 0 | AF25: =SUM(AB25:AE25) -> 3.9540654
D26: 税后蒸汽收入（万元） | E26: =E24/(1+E25/100) -> 0 | H26: 尿素耗用（万吨） | I26: =(0.016*I18+0.09)/100*K18*12%/85%*2.354*0 -> 0 | J26: 尿素单价（元/吨） | K26: =T$61 -> 2200 | L26: 尿素费用（万元） | M26: =I26*K26 -> 0 | N26: 尿素税率% | O26: 13 | P26: 税后金额（万元） | Q26: =M26/(1+O26/100) -> 0 | S26: 灰渣总量（t/h） | T26: =IFERROR($T$6/SUM($AQ$344:$AR$344)*10000*$G$90/100,) -> 0 | U26: 41.99 | V26: 0 | Z26: 炉渣销量 | AA26: 万吨 | AB26: =I20 -> 4.2672599 | AC26: =I44 -> 0.3563297 | AD26: =I68 -> 0 | AE26: =I92 -> 0 | AF26: =SUM(AB26:AE26) -> 4.6235896
A27: 德保 | B27: =$B$112 -> 东怀 | C27: =INDEX($B$111:$Q$131,MATCH($B27,$B$111:$B$131,0),MATCH(C$2,$B$111:$Q$111,0)) -> 2482.3501 | D27: {=INDEX($B$111:$Q$131,MATCH($B27,$B$111:$B$131,0),COLUMN($D$2))} -> 0.12909954 | E27: =C27*D27 -> 320.47026 | F27: =INDEX($B$111:$Q$131,MATCH($B27,$B$111:$B$131,0),MATCH(F$2,$B$111:$Q$111,0)) -> 9.05 | G27: =INDEX($B$111:$Q$131,MATCH($B27,$B$111:$B$131,0),MATCH(G$2,$B$111:$Q$111,0)) -> 53.753421 | H27: =INDEX($B$111:$Q$131,MATCH($B27,$B$111:$B$131,0),MATCH(H$2,$B$111:$Q$111,0)) -> 1.5392982 | I27: =INDEX($B$111:$Q$131,MATCH($B27,$B$111:$B$131,0),MATCH(I$2,$B$111:$Q$111,0)) -> 20.240833 | J27: =IFERROR(K27/K42*100,) -> 0 | K27: 0 | L27: 0 | M27: 0 | N27: =IF(P27>0,INDEX($B$111:$Z$131,MATCH(B27,$B$111:$B$131,0),MATCH($Z$111,$B$111:$Z$111,0))*C27*K27,C27*D27*K27) -> 0 | O27: =P27*K27 -> 0 | P27: {=INDEX($B$111:$AF$131,MATCH($B27,$B$111:$B$131,0),COLUMN($AA$111))} -> 35 | Q27: =SUM(N27:O27) -> 0 | S27: 石油焦比例（%） | T27: {=SUMPRODUCT((B3:B17="石油焦")*1,J3:J17)} -> 0 | U27: 5 | V27: 0 | Z27: 石膏销量 | AA27: 万吨 | AB27: =I21 -> 1.0066363 | AC27: =I45 -> 0.28767855 | AD27: =I69 -> 0 | AF27: =SUM(AB27:AE27) -> 1.2943149
A28: 发电量 | B28: =$B$113 -> 跃进 | C28: =INDEX($B$111:$Q$131,MATCH($B28,$B$111:$B$131,0),MATCH(C$2,$B$111:$Q$111,0)) -> 1800 | D28: {=INDEX($B$111:$Q$131,MATCH($B28,$B$111:$B$131,0),COLUMN($D$2))} -> 0.13777778 | E28: =C28*D28 -> 248 | F28: =INDEX($B$111:$Q$131,MATCH($B28,$B$111:$B$131,0),MATCH(F$2,$B$111:$Q$111,0)) -> 9.9 | G28: =INDEX($B$111:$Q$131,MATCH($B28,$B$111:$B$131,0),MATCH(G$2,$B$111:$Q$111,0)) -> 59.606917 | H28: =INDEX($B$111:$Q$131,MATCH($B28,$B$111:$B$131,0),MATCH(H$2,$B$111:$Q$111,0)) -> 0.41611229 | I28: =INDEX($B$111:$Q$131,MATCH($B28,$B$111:$B$131,0),MATCH(I$2,$B$111:$Q$111,0)) -> 16.798781 | J28: =IFERROR(K28/K42*100,) -> 0 | K28: 0 | L28: 0 | M28: 0 | N28: =IF(P28>0,INDEX($B$111:$Z$131,MATCH(B28,$B$111:$B$131,0),MATCH($Z$111,$B$111:$Z$111,0))*C28*K28,C28*D28*K28) -> 0 | O28: =P28*K28 -> 0 | P28: {=INDEX($B$111:$AF$131,MATCH($B28,$B$111:$B$131,0),COLUMN($AA$111))} -> 50 | Q28: =SUM(N28:O28) -> 0 | S28: 石油焦比例（%） | T28: {=SUMPRODUCT((B27:B41="石油焦")*1,J27:J41)} -> 0 | U28: 5 | V28: 0 | Z28: 硫酸铵销量 | AA28: 万吨 | AE28: =I93 -> 0 | AF28: =SUM(AB28:AE28) -> 0
A29: =AP211 -> 38174.131 | B29: =$B$114 -> 州景 | C29: =INDEX($B$111:$Q$131,MATCH($B29,$B$111:$B$131,0),MATCH(C$2,$B$111:$Q$111,0)) -> 0 | D29: {=INDEX($B$111:$Q$131,MATCH($B29,$B$111:$B$131,0),COLUMN($D$2))} -> 0 | E29: =C29*D29 -> 0 | F29: =INDEX($B$111:$Q$131,MATCH($B29,$B$111:$B$131,0),MATCH(F$2,$B$111:$Q$111,0)) -> 15.681 | G29: =INDEX($B$111:$Q$131,MATCH($B29,$B$111:$B$131,0),MATCH(G$2,$B$111:$Q$111,0)) -> 65.22 | H29: =INDEX($B$111:$Q$131,MATCH($B29,$B$111:$B$131,0),MATCH(H$2,$B$111:$Q$111,0)) -> 0.63 | I29: =INDEX($B$111:$Q$131,MATCH($B29,$B$111:$B$131,0),MATCH(I$2,$B$111:$Q$111,0)) -> 58.6 | J29: =IFERROR(K29/K42*100,) -> 0 | K29: 0 | L29: 0 | M29: 0 | N29: =IF(P29>0,INDEX($B$111:$Z$131,MATCH(B29,$B$111:$B$131,0),MATCH($Z$111,$B$111:$Z$111,0))*C29*K29,C29*D29*K29) -> 0 | O29: =P29*K29 -> 0 | P29: {=INDEX($B$111:$AF$131,MATCH($B29,$B$111:$B$131,0),COLUMN($AA$111))} -> 35 | Q29: =SUM(N29:O29) -> 0 | S29: 石油焦比例（%） | T29: {=SUMPRODUCT((B51:B65="石油焦")*1,J51:J65)} -> 0 | U29: 5 | V29: 0 | Z29: 蒸汽销量 | AA29: 万吨 | AB29: =E22 -> 0 | AC29: =E46 -> 0 | AD29: =E70 -> 0 | AE29: =E94 -> 0 | AF29: =SUM(AB29:AE29) -> 0
A30: 综合厂用电率 | B30: =$B$115 -> 那荷 | C30: =INDEX($B$111:$Q$131,MATCH($B30,$B$111:$B$131,0),MATCH(C$2,$B$111:$Q$111,0)) -> 0 | D30: {=INDEX($B$111:$Q$131,MATCH($B30,$B$111:$B$131,0),COLUMN($D$2))} -> 0 | E30: =C30*D30 -> 0 | F30: =INDEX($B$111:$Q$131,MATCH($B30,$B$111:$B$131,0),MATCH(F$2,$B$111:$Q$111,0)) -> 8.93 | G30: =INDEX($B$111:$Q$131,MATCH($B30,$B$111:$B$131,0),MATCH(G$2,$B$111:$Q$111,0)) -> 71.46 | H30: =INDEX($B$111:$Q$131,MATCH($B30,$B$111:$B$131,0),MATCH(H$2,$B$111:$Q$111,0)) -> 0.34 | I30: =INDEX($B$111:$Q$131,MATCH($B30,$B$111:$B$131,0),MATCH(I$2,$B$111:$Q$111,0)) -> 56.85 | J30: =IFERROR(K30/K42*100,) -> 0 | K30: 0 | L30: 0 | M30: 0 | N30: =IF(P30>0,INDEX($B$111:$Z$131,MATCH(B30,$B$111:$B$131,0),MATCH($Z$111,$B$111:$Z$111,0))*C30*K30,C30*D30*K30) -> 0 | O30: =P30*K30 -> 0 | P30: {=INDEX($B$111:$AF$131,MATCH($B30,$B$111:$B$131,0),COLUMN($AA$111))} -> 50 | Q30: =SUM(N30:O30) -> 0 | S30: 石油焦比例（%） | T30: {=SUMPRODUCT((B75:B89="石油焦")*1,J75:J89)} -> 0 | U30: 5 | V30: 0 | Z30: 炉灰倒运量 | AA30: 万吨 | AB30: =I22 -> 5.0574932 | AC30: =I46 -> 5.4688733 | AD30: =I70 -> 0 | AE30: =I94 -> 0 | AF30: =SUM(AB30:AE30) -> 10.526367
A31: 6.2584823 | B31: =$B$116 -> 褐煤2（云）长协 | C31: =INDEX($B$111:$Q$131,MATCH($B31,$B$111:$B$131,0),MATCH(C$2,$B$111:$Q$111,0)) -> 2400 | D31: {=INDEX($B$111:$Q$131,MATCH($B31,$B$111:$B$131,0),COLUMN($D$2))} -> 0.123 | E31: =C31*D31 -> 295.2 | F31: =INDEX($B$111:$Q$131,MATCH($B31,$B$111:$B$131,0),MATCH(F$2,$B$111:$Q$111,0)) -> 19.2 | G31: =INDEX($B$111:$Q$131,MATCH($B31,$B$111:$B$131,0),MATCH(G$2,$B$111:$Q$111,0)) -> 32.974564 | H31: =INDEX($B$111:$Q$131,MATCH($B31,$B$111:$B$131,0),MATCH(H$2,$B$111:$Q$111,0)) -> 0.80500871 | I31: =INDEX($B$111:$Q$131,MATCH($B31,$B$111:$B$131,0),MATCH(I$2,$B$111:$Q$111,0)) -> 28.483232 | J31: =IFERROR(K31/K42*100,) -> 35.956197 | K31: 9 | L31: {=LOOKUP(1,0/($B$111:$B$131=$B31),$L$111:$L$131)} -> 9 | M31: 0 | N31: =IF(P31>0,INDEX($B$111:$Z$131,MATCH(B31,$B$111:$B$131,0),MATCH($Z$111,$B$111:$Z$111,0))*C31*K31,C31*D31*K31) -> 2656.8 | O31: =P31*K31 -> 0 | P31: {=INDEX($B$111:$AF$131,MATCH($B31,$B$111:$B$131,0),COLUMN($AA$111))} -> 0 | Q31: =SUM(N31:O31) -> 2656.8 | S31: 水分% | T31: =F18 -> 12.226835 | U31: =IF(A5>0,25,0) -> 25 | V31: 0 | Z31: 炉渣倒运量 | AA31: 万吨 | AB31: =I23 -> 6.9540532 | AC31: =I47 -> 0.34370466 | AD31: =I71 -> 0 | AE31: =I95 -> 0 | AF31: =SUM(AB31:AE31) -> 7.2977579
A32: 发电标煤耗 | B32: =$B$117 -> 褐煤3（云）长协 | C32: =INDEX($B$111:$Q$131,MATCH($B32,$B$111:$B$131,0),MATCH(C$2,$B$111:$Q$111,0)) -> 3200 | D32: {=INDEX($B$111:$Q$131,MATCH($B32,$B$111:$B$131,0),COLUMN($D$2))} -> 0.133 | E32: =C32*D32 -> 425.6 | F32: =INDEX($B$111:$Q$131,MATCH($B32,$B$111:$B$131,0),MATCH(F$2,$B$111:$Q$111,0)) -> 19.15 | G32: =INDEX($B$111:$Q$131,MATCH($B32,$B$111:$B$131,0),MATCH(G$2,$B$111:$Q$111,0)) -> 23.873821 | H32: =INDEX($B$111:$Q$131,MATCH($B32,$B$111:$B$131,0),MATCH(H$2,$B$111:$Q$111,0)) -> 0.84706369 | I32: =INDEX($B$111:$Q$131,MATCH($B32,$B$111:$B$131,0),MATCH(I$2,$B$111:$Q$111,0)) -> 30.507667 | J32: =IFERROR(K32/K42*100,) -> 11.985399 | K32: 3 | L32: {=LOOKUP(1,0/($B$111:$B$131=$B32),$L$111:$L$131)} -> 3 | M32: 0 | N32: =IF(P32>0,INDEX($B$111:$Z$131,MATCH(B32,$B$111:$B$131,0),MATCH($Z$111,$B$111:$Z$111,0))*C32*K32,C32*D32*K32) -> 1276.8 | O32: =P32*K32 -> 0 | P32: {=INDEX($B$111:$AF$131,MATCH($B32,$B$111:$B$131,0),COLUMN($AA$111))} -> 0 | Q32: =SUM(N32:O32) -> 1276.8 | S32: 水分% | T32: =F42 -> 19.960148 | U32: =IF(A29>0,35,0) -> 35 | V32: 0 | Z32: 石膏倒运量 | AA32: 万吨 | AB32: =I24 -> 1.6424067 | AC32: =I48 -> 0.20041762 | AD32: =I72 -> 0 | AF32: =SUM(AB32:AE32) -> 1.8428243
A33: =AP204 -> 299.15583 | B33: =$B$118 -> 褐煤3（云） | C33: =INDEX($B$111:$Q$131,MATCH($B33,$B$111:$B$131,0),MATCH(C$2,$B$111:$Q$111,0)) -> 3200 | D33: {=INDEX($B$111:$Q$131,MATCH($B33,$B$111:$B$131,0),COLUMN($D$2))} -> 0.1333 | E33: =C33*D33 -> 426.56 | F33: =INDEX($B$111:$Q$131,MATCH($B33,$B$111:$B$131,0),MATCH(F$2,$B$111:$Q$111,0)) -> 19.15 | G33: =INDEX($B$111:$Q$131,MATCH($B33,$B$111:$B$131,0),MATCH(G$2,$B$111:$Q$111,0)) -> 23.873821 | H33: =INDEX($B$111:$Q$131,MATCH($B33,$B$111:$B$131,0),MATCH(H$2,$B$111:$Q$111,0)) -> 0.84706369 | I33: =INDEX($B$111:$Q$131,MATCH($B33,$B$111:$B$131,0),MATCH(I$2,$B$111:$Q$111,0)) -> 30.507667 | J33: =IFERROR(K33/K42*100,) -> 31.961064 | K33: 8 | L33: {=LOOKUP(1,0/($B$111:$B$131=$B33),$L$111:$L$131)} -> 8 | M33: 0 | N33: =IF(P33>0,INDEX($B$111:$Z$131,MATCH(B33,$B$111:$B$131,0),MATCH($Z$111,$B$111:$Z$111,0))*C33*K33,C33*D33*K33) -> 3412.48 | O33: =P33*K33 -> 0 | P33: {=INDEX($B$111:$AF$131,MATCH($B33,$B$111:$B$131,0),COLUMN($AA$111))} -> 0 | Q33: =SUM(N33:O33) -> 3412.48 | S33: 水分% | T33: =F66 -> 0 | U33: =IF(A53>0,30,0) -> 0 | V33: 0 | Z33: 硫酸铵库存 | AA33: 万吨 | AB33: =E26 -> 0 | AE33: =I96 -> 0 | AF33: =SUM(AB33:AE33) -> 0
A34: 自产比例（%） | B34: =$B$119 -> 褐煤32（港1） | C34: =INDEX($B$111:$Q$131,MATCH($B34,$B$111:$B$131,0),MATCH(C$2,$B$111:$Q$111,0)) -> 3200 | D34: {=INDEX($B$111:$Q$131,MATCH($B34,$B$111:$B$131,0),COLUMN($D$2))} -> 0.17035 | E34: =C34*D34 -> 545.12 | F34: =INDEX($B$111:$Q$131,MATCH($B34,$B$111:$B$131,0),MATCH(F$2,$B$111:$Q$111,0)) -> 32.112709 | G34: =INDEX($B$111:$Q$131,MATCH($B34,$B$111:$B$131,0),MATCH(G$2,$B$111:$Q$111,0)) -> 19.443643 | H34: =INDEX($B$111:$Q$131,MATCH($B34,$B$111:$B$131,0),MATCH(H$2,$B$111:$Q$111,0)) -> 0.77574029 | I34: =INDEX($B$111:$Q$131,MATCH($B34,$B$111:$B$131,0),MATCH(I$2,$B$111:$Q$111,0)) -> 24.82919 | J34: =IFERROR(K34/K42*100,) -> 0 | K34: 0 | L34: {=LOOKUP(1,0/($B$111:$B$131=$B34),$L$111:$L$131)} -> 100 | M34: 0 | N34: =IF(P34>0,INDEX($B$111:$Z$131,MATCH(B34,$B$111:$B$131,0),MATCH($Z$111,$B$111:$Z$111,0))*C34*K34,C34*D34*K34) -> 0 | O34: =P34*K34 -> 0 | P34: {=INDEX($B$111:$AF$131,MATCH($B34,$B$111:$B$131,0),COLUMN($AA$111))} -> 100.32 | Q34: =SUM(N34:O34) -> 0 | S34: 水分% | T34: =F90 -> 0 | U34: =IF(A77>0,20,0) -> 0 | V34: 0 | Z34: 石粉耗用量 | AA34: 万吨 | AB34: =I25 -> 1.3584836 | AC34: =I49 -> 0.2871154 | AD34: =I73 -> 0 | AF34: =SUM(AB34:AE34) -> 1.645599
A35: =(SUMIF($B$27:$B$41,$B$112,$K$27:$K$41)+SUMIF($B$27:$B$41,$B$113,$K$27:$K$41)+SUMIF($B$27:$B$41,$B$114,$K$27:$K$41)+SUMIF($B$27:$B$41,$B$115,$K$27:$K$41))/$K$42*100 -> 0 | B35: =$B$120 -> 褐煤35（港2） | C35: =INDEX($B$111:$Q$131,MATCH($B35,$B$111:$B$131,0),MATCH(C$2,$B$111:$Q$111,0)) -> 3500 | D35: {=INDEX($B$111:$Q$131,MATCH($B35,$B$111:$B$131,0),COLUMN($D$2))} -> 0.17456286 | E35: =C35*D35 -> 610.97 | F35: =INDEX($B$111:$Q$131,MATCH($B35,$B$111:$B$131,0),MATCH(F$2,$B$111:$Q$111,0)) -> 29.814059 | G35: =INDEX($B$111:$Q$131,MATCH($B35,$B$111:$B$131,0),MATCH(G$2,$B$111:$Q$111,0)) -> 17.717186 | H35: =INDEX($B$111:$Q$131,MATCH($B35,$B$111:$B$131,0),MATCH(H$2,$B$111:$Q$111,0)) -> 0.78167601 | I35: =INDEX($B$111:$Q$131,MATCH($B35,$B$111:$B$131,0),MATCH(I$2,$B$111:$Q$111,0)) -> 26.875931 | J35: =IFERROR(K35/K42*100,) -> 0 | K35: 0 | L35: {=LOOKUP(1,0/($B$111:$B$131=$B35),$L$111:$L$131)} -> 100 | M35: 0 | N35: =IF(P35>0,INDEX($B$111:$Z$131,MATCH(B35,$B$111:$B$131,0),MATCH($Z$111,$B$111:$Z$111,0))*C35*K35,C35*D35*K35) -> 0 | O35: =P35*K35 -> 0 | P35: {=INDEX($B$111:$AF$131,MATCH($B35,$B$111:$B$131,0),COLUMN($AA$111))} -> 100.32 | Q35: =SUM(N35:O35) -> 0 | T35: 0 | U35: 0 | V35: 0 | Z35: 尿素耗用量 | AA35: 万吨 | AB35: =I26 -> 0 | AC35: =I50 -> 0.028516892 | AD35: =I74 -> 0 | AE35: =I98 -> 0 | AF35: =SUM(AB35:AE35) -> 0.028516892
A36: 利润（万元） | B36: =$B$121 -> 褐煤38（港3） | C36: =INDEX($B$111:$Q$131,MATCH($B36,$B$111:$B$131,0),MATCH(C$2,$B$111:$Q$111,0)) -> 3800 | D36: {=INDEX($B$111:$Q$131,MATCH($B36,$B$111:$B$131,0),COLUMN($D$2))} -> 0.1707 | E36: =C36*D36 -> 648.66 | F36: =INDEX($B$111:$Q$131,MATCH($B36,$B$111:$B$131,0),MATCH(F$2,$B$111:$Q$111,0)) -> 34.679691 | G36: =INDEX($B$111:$Q$131,MATCH($B36,$B$111:$B$131,0),MATCH(G$2,$B$111:$Q$111,0)) -> 8.6727633 | H36: =INDEX($B$111:$Q$131,MATCH($B36,$B$111:$B$131,0),MATCH(H$2,$B$111:$Q$111,0)) -> 0.82970573 | I36: =INDEX($B$111:$Q$131,MATCH($B36,$B$111:$B$131,0),MATCH(I$2,$B$111:$Q$111,0)) -> 28.638706 | J36: =IFERROR(K36/K42*100,) -> 0 | K36: 0 | L36: {=LOOKUP(1,0/($B$111:$B$131=$B36),$L$111:$L$131)} -> 100 | M36: 0 | N36: =IF(P36>0,INDEX($B$111:$Z$131,MATCH(B36,$B$111:$B$131,0),MATCH($Z$111,$B$111:$Z$111,0))*C36*K36,C36*D36*K36) -> 0 | O36: =P36*K36 -> 0 | P36: {=INDEX($B$111:$AF$131,MATCH($B36,$B$111:$B$131,0),COLUMN($AA$111))} -> 100.32 | Q36: =SUM(N36:O36) -> 0 | T36: 0 | U36: 0 | V36: 0 | Z36: 液氨耗用量 | AA36: 万吨 | AE36: =I97 -> 0 | AF36: =SUM(AB36:AE36) -> 0
A37: =C106 -> 4396.9912 | B37: =$B$122 -> 褐煤46 | C37: =INDEX($B$111:$Q$131,MATCH($B37,$B$111:$B$131,0),MATCH(C$2,$B$111:$Q$111,0)) -> 4600 | D37: {=INDEX($B$111:$Q$131,MATCH($B37,$B$111:$B$131,0),COLUMN($D$2))} -> 0.1625087 | E37: =C37*D37 -> 747.54 | F37: =INDEX($B$111:$Q$131,MATCH($B37,$B$111:$B$131,0),MATCH(F$2,$B$111:$Q$111,0)) -> 23.091665 | G37: =INDEX($B$111:$Q$131,MATCH($B37,$B$111:$B$131,0),MATCH(G$2,$B$111:$Q$111,0)) -> 10.878752 | H37: =INDEX($B$111:$Q$131,MATCH($B37,$B$111:$B$131,0),MATCH(H$2,$B$111:$Q$111,0)) -> 0.20812534 | I37: =INDEX($B$111:$Q$131,MATCH($B37,$B$111:$B$131,0),MATCH(I$2,$B$111:$Q$111,0)) -> 32.849465 | J37: =IFERROR(K37/K42*100,) -> 20.09734 | K37: 5.0304557 | L37: {=LOOKUP(1,0/($B$111:$B$131=$B37),$L$111:$L$131)} -> 100 | M37: 0 | N37: =IF(P37>0,INDEX($B$111:$Z$131,MATCH(B37,$B$111:$B$131,0),MATCH($Z$111,$B$111:$Z$111,0))*C37*K37,C37*D37*K37) -> 3255.8115 | O37: =P37*K37 -> 504.65531 | P37: {=INDEX($B$111:$AF$131,MATCH($B37,$B$111:$B$131,0),COLUMN($AA$111))} -> 100.32 | Q37: =SUM(N37:O37) -> 3760.4668 | T37: 0 | U37: 0 | V37: 0 | Z37: 炉灰价格 | AA37: 元/吨 | AB37: =K19 -> -20 | AC37: =K43 -> -45 | AD37: =K67 -> -20 | AE37: =K91 -> 20
A38: 锅炉效率（%） | B38: =$B$123 -> 烟煤55 | C38: =INDEX($B$111:$Q$131,MATCH($B38,$B$111:$B$131,0),MATCH(C$2,$B$111:$Q$111,0)) -> 5500 | D38: {=INDEX($B$111:$Q$131,MATCH($B38,$B$111:$B$131,0),COLUMN($D$2))} -> 0.16724 | E38: =C38*D38 -> 919.82 | F38: =INDEX($B$111:$Q$131,MATCH($B38,$B$111:$B$131,0),MATCH(F$2,$B$111:$Q$111,0)) -> 10.316451 | G38: =INDEX($B$111:$Q$131,MATCH($B38,$B$111:$B$131,0),MATCH(G$2,$B$111:$Q$111,0)) -> 19.875802 | H38: =INDEX($B$111:$Q$131,MATCH($B38,$B$111:$B$131,0),MATCH(H$2,$B$111:$Q$111,0)) -> 0.47663777 | I38: =INDEX($B$111:$Q$131,MATCH($B38,$B$111:$B$131,0),MATCH(I$2,$B$111:$Q$111,0)) -> 25.313893 | J38: =IFERROR(K38/K42*100,) -> 0 | K38: 0 | L38: {=LOOKUP(1,0/($B$111:$B$131=$B38),$L$111:$L$131)} -> 100 | M38: 0 | N38: =IF(P38>0,INDEX($B$111:$Z$131,MATCH(B38,$B$111:$B$131,0),MATCH($Z$111,$B$111:$Z$111,0))*C38*K38,C38*D38*K38) -> 0 | O38: =P38*K38 -> 0 | P38: {=INDEX($B$111:$AF$131,MATCH($B38,$B$111:$B$131,0),COLUMN($AA$111))} -> 100.32 | Q38: =SUM(N38:O38) -> 0 | T38: 0 | U38: 0 | V38: 0 | Z38: 炉渣价格 | AA38: 元/吨 | AB38: =K20 -> -8 | AC38: =K44 -> -20 | AD38: =K68 -> -8 | AE38: =K92 -> 0
A39: =AP205*100 -> 92.821233 | B39: =$B$124 -> 烟煤50备 | C39: =INDEX($B$111:$Q$131,MATCH($B39,$B$111:$B$131,0),MATCH(C$2,$B$111:$Q$111,0)) -> 5000 | D39: {=INDEX($B$111:$Q$131,MATCH($B39,$B$111:$B$131,0),COLUMN($D$2))} -> 0 | E39: =C39*D39 -> 0 | F39: =INDEX($B$111:$Q$131,MATCH($B39,$B$111:$B$131,0),MATCH(F$2,$B$111:$Q$111,0)) -> 0 | G39: =INDEX($B$111:$Q$131,MATCH($B39,$B$111:$B$131,0),MATCH(G$2,$B$111:$Q$111,0)) -> 0 | H39: =INDEX($B$111:$Q$131,MATCH($B39,$B$111:$B$131,0),MATCH(H$2,$B$111:$Q$111,0)) -> 0 | I39: =INDEX($B$111:$Q$131,MATCH($B39,$B$111:$B$131,0),MATCH(I$2,$B$111:$Q$111,0)) -> 0 | J39: =IFERROR(K39/K42*100,) -> 0 | K39: 0 | L39: {=LOOKUP(1,0/($B$111:$B$131=$B39),$L$111:$L$131)} -> 0 | M39: 0 | N39: =IF(P39>0,INDEX($B$111:$Z$131,MATCH(B39,$B$111:$B$131,0),MATCH($Z$111,$B$111:$Z$111,0))*C39*K39,C39*D39*K39) -> 0 | O39: =P39*K39 -> 0 | P39: {=INDEX($B$111:$AF$131,MATCH($B39,$B$111:$B$131,0),COLUMN($AA$111))} -> 0 | Q39: =SUM(N39:O39) -> 0 | T39: 0 | U39: 0 | V39: 0 | Z39: 石膏价格 | AA39: 元/吨 | AB39: =K21 -> -5 | AC39: =K45 -> -30 | AD39: =K69 -> -5
A40: 汽机热耗率 | B40: =$B$125 -> 烟煤55备 | C40: =INDEX($B$111:$Q$131,MATCH($B40,$B$111:$B$131,0),MATCH(C$2,$B$111:$Q$111,0)) -> 5500 | D40: {=INDEX($B$111:$Q$131,MATCH($B40,$B$111:$B$131,0),COLUMN($D$2))} -> 0 | E40: =C40*D40 -> 0 | F40: =INDEX($B$111:$Q$131,MATCH($B40,$B$111:$B$131,0),MATCH(F$2,$B$111:$Q$111,0)) -> 0 | G40: =INDEX($B$111:$Q$131,MATCH($B40,$B$111:$B$131,0),MATCH(G$2,$B$111:$Q$111,0)) -> 0 | H40: =INDEX($B$111:$Q$131,MATCH($B40,$B$111:$B$131,0),MATCH(H$2,$B$111:$Q$111,0)) -> 0 | I40: =INDEX($B$111:$Q$131,MATCH($B40,$B$111:$B$131,0),MATCH(I$2,$B$111:$Q$111,0)) -> 0 | J40: =IFERROR(K40/K42*100,) -> 0 | K40: 0 | L40: {=LOOKUP(1,0/($B$111:$B$131=$B40),$L$111:$L$131)} -> 0 | M40: 0 | N40: =IF(P40>0,INDEX($B$111:$Z$131,MATCH(B40,$B$111:$B$131,0),MATCH($Z$111,$B$111:$Z$111,0))*C40*K40,C40*D40*K40) -> 0 | O40: =P40*K40 -> 0 | P40: {=INDEX($B$111:$AF$131,MATCH($B40,$B$111:$B$131,0),COLUMN($AA$111))} -> 0 | Q40: =SUM(N40:O40) -> 0 | T40: 0 | U40: 0 | V40: 0 | Z40: 硫酸铵价格 | AA40: 元/吨 | AE40: =K93 -> 600
A41: =AP206 -> 8040.4806 | B41: =$B$127 -> 石油焦 | C41: =INDEX($B$111:$Q$131,MATCH($B41,$B$111:$B$131,0),MATCH(C$2,$B$111:$Q$111,0)) -> 7256.4478 | D41: {=INDEX($B$111:$Q$131,MATCH($B41,$B$111:$B$131,0),COLUMN($D$2))} -> 0 | E41: =C41*D41 -> 0 | F41: =INDEX($B$111:$Q$131,MATCH($B41,$B$111:$B$131,0),MATCH(F$2,$B$111:$Q$111,0)) -> 0 | G41: =INDEX($B$111:$Q$131,MATCH($B41,$B$111:$B$131,0),MATCH(G$2,$B$111:$Q$111,0)) -> 0 | H41: =INDEX($B$111:$Q$131,MATCH($B41,$B$111:$B$131,0),MATCH(H$2,$B$111:$Q$111,0)) -> 0 | I41: =INDEX($B$111:$Q$131,MATCH($B41,$B$111:$B$131,0),MATCH(I$2,$B$111:$Q$111,0)) -> 0 | J41: =IFERROR(K41/K42*100,) -> 0 | K41: 0 | L41: {=LOOKUP(1,0/($B$111:$B$131=$B41),$L$111:$L$131)} -> 0 | M41: 0 | N41: =IF(P41>0,INDEX($B$111:$Z$131,MATCH(B41,$B$111:$B$131,0),MATCH($Z$111,$B$111:$Z$111,0))*C41*K41,C41*D41*K41) -> 0 | O41: =P41*K41 -> 0 | P41: {=INDEX($B$111:$AF$131,MATCH($B41,$B$111:$B$131,0),COLUMN($AA$111))} -> 0 | Q41: =SUM(N41:O41) -> 0 | T41: 0 | U41: 0 | V41: 0 | Z41: 蒸汽价格 | AA41: 元/吨 | AB41: =E23 -> 168 | AC41: =E47 -> 168 | AD41: =E71 -> 168 | AE41: =E95 -> 168
B42: 加权平均 | C42: =IFERROR(SUMPRODUCT(C27:C41,K27:K41)/SUM(K27:K41),) -> 3193.7132 | D42: =IFERROR(SUMPRODUCT(C27:C41,D27:D41,K27:K41)/SUMPRODUCT(C27:C41,K27:K41),) -> 0.13893587 | E42: =IFERROR(SUMPRODUCT(C27:C41,E27:E41,K27:K41)/SUMPRODUCT(C27:C41,K27:K41),) -> 483.86436 | F42: =IFERROR(SUMPRODUCT(F27:F41,K27:K41)/SUM(K27:K41),) -> 19.960148 | G42: =IFERROR(SUMPRODUCT(G27:G41,K27:K41)/SUM(K27:K41),) -> 24.534439 | H42: =IFERROR(SUMPRODUCT(H27:H41,K27:K41)/SUM(K27:K41),) -> 0.70353271 | I42: =IFERROR(SUMPRODUCT(I27:I41,K27:K41)/SUM(K27:K41),) -> 30.250396 | J42: =IFERROR(SUM(J27:J41),) -> 100 | K42: =IFERROR(SUM(K27:K41),) -> 25.030456 | L42: =SUM(L27:L41) -> 520 | M42: =SUM(M27:M41) -> 0 | N42: =SUM(N27:N41) -> 10601.892 | O42: =SUM(O27:O41) -> 504.65531 | P42: =IFERROR(SUMPRODUCT(P27:P41,K27:K41)/SUM(K27:K41),) -> 20.161651 | Q42: =SUM(Q27:Q41) -> 11106.547 | R42: =SUM(R27:R41) -> 0 | T42: 0 | U42: 0 | V42: 0 | Z42: 炉灰倒运单价 | AA42: 元/吨 | AB42: =K22 -> 7.9 | AC42: =K46 -> 30.92 | AD42: =K70 -> 7.9 | AE42: =K94 -> 0.9
B43: 炉灰占比% | C43: =U$47 -> 90 | D43: 炉灰产量（万吨） | E43: =$K42*$G42/100*C43/100 -> 5.5269738 | F43: 炉灰销售% | G43: =U$51 -> 25.788412 | H43: 炉灰销量（万吨） | I43: =E43*G43/100 -> 1.4253188 | J43: 炉灰价格（元/吨） | K43: =U$54 -> -45 | L43: 炉灰收入（万元） | M43: =I43*K43 -> -64.139346 | N43: 炉灰税率% | O43: 13 | P43: 税后金额（万元） | Q43: =M43/(1+O43/100) -> -56.760483 | Z43: 炉渣倒运单价 | AA43: 元/吨 | AB43: =K23 -> 7.9 | AC43: =K47 -> 30.92 | AD43: =K71 -> 7.9 | AE43: =K95 -> 0.9
B44: 炉渣占比% | C44: =100-C43 -> 10 | D44: 炉渣产量（万吨） | E44: =$K42*$G42/100*C44/100 -> 0.6141082 | F44: 炉渣销售% | G44: =U$52 -> 58.023928 | H44: 炉渣销量（万吨） | I44: =E44*G44/100 -> 0.3563297 | J44: 炉渣价格（元/吨） | K44: =U$55 -> -20 | L44: 炉渣收入（万元） | M44: =I44*K44 -> -7.126594 | N44: 炉渣税率% | O44: 13 | P44: 税后金额（万元） | Q44: =M44/(1+O44/100) -> -6.3067203 | Z44: 石膏倒运单价 | AA44: 元/吨 | AB44: =K24 -> 7.9 | AC44: =K48 -> 30.92 | AD44: =K72 -> 7.9
B45: 钙硫比 | C45: =U$49 -> 1.6304348 | D45: 石膏产量（万吨） | E45: =C46*I49 -> 0.48809617 | F45: 石膏销售% | G45: =U$53 -> 58.938907 | H45: 石膏销量（万吨） | I45: =E45*G45/100 -> 0.28767855 | J45: 石膏价格（元/吨） | K45: =U$56 -> -30 | L45: 石膏收入（万元） | M45: =I45*K45 -> -8.6303565 | N45: 硫酸铵税率% | O45: 13 | P45: 税后金额（万元） | Q45: =M45/(1+O45/100) -> -7.6374837 | S45: 副产品参数设置 | Z45: 硫酸铵倒运单价 | AA45: 元/吨 | AE45: =K96 -> 0
B46: 石膏石粉比 | C46: =U$50 -> 1.7 | D46: 销售蒸汽（万吨） | E46: =U$62 -> 0 | F46: 炉灰调湿比例% | G46: =U64 -> 25 | H46: 炉灰倒运量（万吨） | I46: =(E43-I43)/(1-G46/100) -> 5.4688733 | J46: 炉灰倒运单价（元/吨） | K46: =U$57 -> 30.92 | L46: 炉灰倒运费（万元） | M46: =I46*K46 -> 169.09756 | N46: 炉灰倒运税率% | O46: 6 | P46: 税后金额（万元） | Q46: =M46/(1+O46/100) -> 159.526 | S46: 项目 | T46: 百矿 | U46: 德保 | V46: 银海 | W46: 田东 | Z46: 石粉单价 | AA46: 元/吨 | AB46: =K25 -> 67 | AC46: =K49 -> 86 | AD46: =K73 -> 67
D47: 蒸汽单价（元/吨） | E47: =U$63 -> 168 | F47: 炉渣调湿比例% | G47: =U65 -> 25 | H47: 炉渣倒运量（万吨） | I47: =(E44-I44)/(1-G47/100) -> 0.34370466 | J47: 炉渣倒运单价（元/吨） | K47: =U$58 -> 30.92 | L47: 炉渣倒运费（万元） | M47: =I47*K47 -> 10.627348 | N47: 炉渣倒运税率% | O47: 6 | P47: 税后金额（万元） | Q47: =M47/(1+O47/100) -> 10.0258 | S47: 炉灰占比% | T47: 40 | U47: 90 | V47: 60 | W47: 90 | Z47: 尿素单价 | AA47: 元/吨 | AB47: =K26 -> 2200 | AC47: =K50 -> 2500 | AD47: =K74 -> 0 | AE47: =K98 -> 0
D48: 蒸汽收入（万元） | E48: =E46*E47 -> 0 | H48: 石膏倒运量（万吨） | I48: =E45-I45 -> 0.20041762 | J48: 石膏倒运单价（元/吨） | K48: =U$59 -> 30.92 | L48: 石膏倒运费（万元） | M48: =I48*K48 -> 6.1969129 | N48: 石膏运税率% | O48: 6 | P48: 税后金额（万元） | Q48: =M48/(1+O48/100) -> 5.8461442 | S48: 炉渣占比% | T48: 60 | U48: 10 | V48: 40 | W48: 10 | Z48: 液氨单价 | AA48: 元/吨 | AE48: =K97 -> 2950
D49: 税率% | E49: 9 | H49: 石粉耗用（万吨） | I49: =H42/100*K42*C45 -> 0.2871154 | J49: 石粉单价（元/吨） | K49: =U$60 -> 86 | L49: 石粉费用（万元） | M49: =I49*K49 -> 24.691924 | N49: 石粉税率% | O49: 13 | P49: 税后金额（万元） | Q49: =M49/(1+O49/100) -> 21.85126 | S49: 钙硫比/氨硫比 | T49: 4.35 | U49: 1.6304348 | V49: 4.35 | W49: 1.1067708 | Z49: 炉灰收入 | AA49: 万元 | AB49: =AB25*AB37 -> -50.574932 | AC49: =AC25*AC37 -> -64.139346 | AD49: =AD25*AD37 -> 0 | AE49: =AE25*AE37 -> 0 | AF49: =SUM(AB49:AE49) -> -114.71428
D50: 税后蒸汽收入（万元） | E50: =E48/(1+E49/100) -> 0 | H50: 尿素耗用（万吨） | I50: =(0.016*I42+0.09)/100*K42*12%/100%*1.654 -> 0.028516892 | J50: 尿素单价（元/吨） | K50: =U$61 -> 2500 | L50: 尿素费用（万元） | M50: =I50*K50 -> 71.292231 | N50: 尿素税率% | O50: 13 | P50: 税后金额（万元） | Q50: =M50/(1+O50/100) -> 63.09047 | S50: 石膏石粉比（硫铵比） | T50: 1.95 | U50: 1.7 | V50: 1.7 | W50: 3.1 | Z50: 炉渣收入 | AA50: 万元 | AB50: =AB26*AB38 -> -34.138079 | AC50: =AC26*AC38 -> -7.126594 | AD50: =AD26*AD38 -> 0 | AE50: =AE26*AE38 -> 0 | AF50: =SUM(AB50:AE50) -> -41.264673
A51: 银海 | B51: =$B$112 -> 东怀 | C51: =INDEX($B$111:$Q$131,MATCH($B51,$B$111:$B$131,0),MATCH(C$2,$B$111:$Q$111,0)) -> 2482.3501 | D51: {=INDEX($B$111:$Q$131,MATCH($B51,$B$111:$B$131,0),COLUMN($D$2)-1)} -> 0.12049076 | E51: =C51*D51 -> 299.10026 | F51: =INDEX($B$111:$Q$131,MATCH($B51,$B$111:$B$131,0),MATCH(F$2,$B$111:$Q$111,0)) -> 9.05 | G51: =INDEX($B$111:$Q$131,MATCH($B51,$B$111:$B$131,0),MATCH(G$2,$B$111:$Q$111,0)) -> 53.753421 | H51: =INDEX($B$111:$Q$131,MATCH($B51,$B$111:$B$131,0),MATCH(H$2,$B$111:$Q$111,0)) -> 1.5392982 | I51: =INDEX($B$111:$Q$131,MATCH($B51,$B$111:$B$131,0),MATCH(I$2,$B$111:$Q$111,0)) -> 20.240833 | J51: =IFERROR(K51/K66*100,) -> 0 | K51: 0 | L51: {=LOOKUP(1,0/($B$111:$B$131=$B51),$L$111:$L$131)} -> 16.550016 | M51: 0 | N51: =IF(P51>0,INDEX($B$111:$Z$131,MATCH(B51,$B$111:$B$131,0),MATCH($Z$111,$B$111:$Z$111,0))*C51*K51,C51*D51*K51) -> 0 | O51: =P51*K51 -> 0 | P51: {=INDEX($B$111:$AF$131,MATCH($B51,$B$111:$B$131,0),COLUMN($AA$111)-1)} -> 13.63 | Q51: =SUM(N51:O51) -> 0 | S51: 炉灰销售% | T51: 40 | U51: 25.788412 | V51: 5 | W51: 88.08189 | Z51: 石膏收入 | AA51: 万元 | AB51: =AB27*AB39 -> -5.0331817 | AC51: =AC27*AC39 -> -8.6303565 | AD51: =AD27*AD39 -> 0 | AE51: =AE27*AE39 -> 0 | AF51: =SUM(AB51:AE51) -> -13.663538
A52: 发电量 | B52: =$B$113 -> 跃进 | C52: =INDEX($B$111:$Q$131,MATCH($B52,$B$111:$B$131,0),MATCH(C$2,$B$111:$Q$111,0)) -> 1800 | D52: {=INDEX($B$111:$Q$131,MATCH($B52,$B$111:$B$131,0),COLUMN($D$2)-1)} -> 0.11937778 | E52: =C52*D52 -> 214.88 | F52: =INDEX($B$111:$Q$131,MATCH($B52,$B$111:$B$131,0),MATCH(F$2,$B$111:$Q$111,0)) -> 9.9 | G52: =INDEX($B$111:$Q$131,MATCH($B52,$B$111:$B$131,0),MATCH(G$2,$B$111:$Q$111,0)) -> 59.606917 | H52: =INDEX($B$111:$Q$131,MATCH($B52,$B$111:$B$131,0),MATCH(H$2,$B$111:$Q$111,0)) -> 0.41611229 | I52: =INDEX($B$111:$Q$131,MATCH($B52,$B$111:$B$131,0),MATCH(I$2,$B$111:$Q$111,0)) -> 16.798781 | J52: =IFERROR(K52/K66*100,) -> 0 | K52: 0 | L52: {=LOOKUP(1,0/($B$111:$B$131=$B52),$L$111:$L$131)} -> 10.304105 | M52: 0 | N52: =IF(P52>0,INDEX($B$111:$Z$131,MATCH(B52,$B$111:$B$131,0),MATCH($Z$111,$B$111:$Z$111,0))*C52*K52,C52*D52*K52) -> 0 | O52: =P52*K52 -> 0 | P52: {=INDEX($B$111:$AF$131,MATCH($B52,$B$111:$B$131,0),COLUMN($AA$111)-1)} -> 16.88 | Q52: =SUM(N52:O52) -> 0 | S52: 炉渣销售% | T52: 45 | U52: 58.023928 | V52: 40 | W52: 92.485984 | Z52: 硫酸铵收入 | AA52: 万元 | AB52: =AB28*AB40 -> 0 | AC52: =AC28*AC40 -> 0 | AD52: =AD28*AD40 -> 0 | AE52: =AE28*AE40 -> 0 | AF52: =SUM(AB52:AE52) -> 0
A53: =AP277 -> 0 | B53: =$B$114 -> 州景 | C53: =INDEX($B$111:$Q$131,MATCH($B53,$B$111:$B$131,0),MATCH(C$2,$B$111:$Q$111,0)) -> 0 | D53: {=INDEX($B$111:$Q$131,MATCH($B53,$B$111:$B$131,0),COLUMN($D$2)-1)} -> 0 | E53: =C53*D53 -> 0 | F53: =INDEX($B$111:$Q$131,MATCH($B53,$B$111:$B$131,0),MATCH(F$2,$B$111:$Q$111,0)) -> 15.681 | G53: =INDEX($B$111:$Q$131,MATCH($B53,$B$111:$B$131,0),MATCH(G$2,$B$111:$Q$111,0)) -> 65.22 | H53: =INDEX($B$111:$Q$131,MATCH($B53,$B$111:$B$131,0),MATCH(H$2,$B$111:$Q$111,0)) -> 0.63 | I53: =INDEX($B$111:$Q$131,MATCH($B53,$B$111:$B$131,0),MATCH(I$2,$B$111:$Q$111,0)) -> 58.6 | J53: =IFERROR(K53/K66*100,) -> 0 | K53: 0 | L53: {=LOOKUP(1,0/($B$111:$B$131=$B53),$L$111:$L$131)} -> 0 | M53: 0 | N53: =IF(P53>0,INDEX($B$111:$Z$131,MATCH(B53,$B$111:$B$131,0),MATCH($Z$111,$B$111:$Z$111,0))*C53*K53,C53*D53*K53) -> 0 | O53: =P53*K53 -> 0 | P53: {=INDEX($B$111:$AF$131,MATCH($B53,$B$111:$B$131,0),COLUMN($AA$111)-1)} -> 12.88 | Q53: =SUM(N53:O53) -> 0 | S53: 石膏销售% | T53: 38 | U53: 58.938907 | V53: 40 | W53: 98.198126 | Z53: 蒸汽收入 | AA53: 万元 | AB53: =AB29*AB41 -> 0 | AC53: =AC29*AC41 -> 0 | AD53: =AD29*AD41 -> 0 | AE53: =AE29*AE41 -> 0 | AF53: =SUM(AB53:AE53) -> 0
A54: 综合厂用电率 | B54: =$B$115 -> 那荷 | C54: =INDEX($B$111:$Q$131,MATCH($B54,$B$111:$B$131,0),MATCH(C$2,$B$111:$Q$111,0)) -> 0 | D54: {=INDEX($B$111:$Q$131,MATCH($B54,$B$111:$B$131,0),COLUMN($D$2)-1)} -> 0 | E54: =C54*D54 -> 0 | F54: =INDEX($B$111:$Q$131,MATCH($B54,$B$111:$B$131,0),MATCH(F$2,$B$111:$Q$111,0)) -> 8.93 | G54: =INDEX($B$111:$Q$131,MATCH($B54,$B$111:$B$131,0),MATCH(G$2,$B$111:$Q$111,0)) -> 71.46 | H54: =INDEX($B$111:$Q$131,MATCH($B54,$B$111:$B$131,0),MATCH(H$2,$B$111:$Q$111,0)) -> 0.34 | I54: =INDEX($B$111:$Q$131,MATCH($B54,$B$111:$B$131,0),MATCH(I$2,$B$111:$Q$111,0)) -> 56.85 | J54: =IFERROR(K54/K66*100,) -> 0 | K54: 0 | L54: {=LOOKUP(1,0/($B$111:$B$131=$B54),$L$111:$L$131)} -> 0 | M54: 0 | N54: =IF(P54>0,INDEX($B$111:$Z$131,MATCH(B54,$B$111:$B$131,0),MATCH($Z$111,$B$111:$Z$111,0))*C54*K54,C54*D54*K54) -> 0 | O54: =P54*K54 -> 0 | P54: {=INDEX($B$111:$AF$131,MATCH($B54,$B$111:$B$131,0),COLUMN($AA$111)-1)} -> 8.43 | Q54: =SUM(N54:O54) -> 0 | S54: 炉灰价格（元/吨） | T54: -20 | U54: -45 | V54: -20 | W54: 20 | Z54: 石粉成本 | AA54: 万元 | AB54: =AB34*AB46 -> 91.018401 | AC54: =AC34*AC46 -> 24.691924 | AD54: =AD34*AD46 -> 0 | AE54: =AE34*AE46 -> 0 | AF54: =SUM(AB54:AE54) -> 115.71033
A55: 9.0735472 | B55: =$B$116 -> 褐煤2（云）长协 | C55: =INDEX($B$111:$Q$131,MATCH($B55,$B$111:$B$131,0),MATCH(C$2,$B$111:$Q$111,0)) -> 2400 | D55: {=INDEX($B$111:$Q$131,MATCH($B55,$B$111:$B$131,0),COLUMN($D$2)-1)} -> 0.123 | E55: =C55*D55 -> 295.2 | F55: =INDEX($B$111:$Q$131,MATCH($B55,$B$111:$B$131,0),MATCH(F$2,$B$111:$Q$111,0)) -> 19.2 | G55: =INDEX($B$111:$Q$131,MATCH($B55,$B$111:$B$131,0),MATCH(G$2,$B$111:$Q$111,0)) -> 32.974564 | H55: =INDEX($B$111:$Q$131,MATCH($B55,$B$111:$B$131,0),MATCH(H$2,$B$111:$Q$111,0)) -> 0.80500871 | I55: =INDEX($B$111:$Q$131,MATCH($B55,$B$111:$B$131,0),MATCH(I$2,$B$111:$Q$111,0)) -> 28.483232 | J55: =IFERROR(K55/K66*100,) -> 0 | K55: 0 | L55: 0 | M55: 0 | N55: =IF(P55>0,INDEX($B$111:$Z$131,MATCH(B55,$B$111:$B$131,0),MATCH($Z$111,$B$111:$Z$111,0))*C55*K55,C55*D55*K55) -> 0 | O55: =P55*K55 -> 0 | P55: {=INDEX($B$111:$AF$131,MATCH($B55,$B$111:$B$131,0),COLUMN($AA$111)-1)} -> 0 | Q55: =SUM(N55:O55) -> 0 | S55: 炉渣价格（元/吨） | T55: -8 | U55: -20 | V55: -8 | W55: 0 | Z55: 尿素成本 | AA55: 万元 | AB55: =AB35*AB47 -> 0 | AC55: =AC35*AC47 -> 71.292231 | AD55: =AD35*AD47 -> 0 | AE55: =AE35*AE47 -> 0 | AF55: =SUM(AB55:AE55) -> 71.292231
A56: 发电标煤耗 | B56: =$B$117 -> 褐煤3（云）长协 | C56: =INDEX($B$111:$Q$131,MATCH($B56,$B$111:$B$131,0),MATCH(C$2,$B$111:$Q$111,0)) -> 3200 | D56: {=INDEX($B$111:$Q$131,MATCH($B56,$B$111:$B$131,0),COLUMN($D$2)-1)} -> 0.133 | E56: =C56*D56 -> 425.6 | F56: =INDEX($B$111:$Q$131,MATCH($B56,$B$111:$B$131,0),MATCH(F$2,$B$111:$Q$111,0)) -> 19.15 | G56: =INDEX($B$111:$Q$131,MATCH($B56,$B$111:$B$131,0),MATCH(G$2,$B$111:$Q$111,0)) -> 23.873821 | H56: =INDEX($B$111:$Q$131,MATCH($B56,$B$111:$B$131,0),MATCH(H$2,$B$111:$Q$111,0)) -> 0.84706369 | I56: =INDEX($B$111:$Q$131,MATCH($B56,$B$111:$B$131,0),MATCH(I$2,$B$111:$Q$111,0)) -> 30.507667 | J56: =IFERROR(K56/K66*100,) -> 0 | K56: 0 | L56: 0 | M56: 0 | N56: =IF(P56>0,INDEX($B$111:$Z$131,MATCH(B56,$B$111:$B$131,0),MATCH($Z$111,$B$111:$Z$111,0))*C56*K56,C56*D56*K56) -> 0 | O56: =P56*K56 -> 0 | P56: {=INDEX($B$111:$AF$131,MATCH($B56,$B$111:$B$131,0),COLUMN($AA$111)-1)} -> 0 | Q56: =SUM(N56:O56) -> 0 | S56: 石膏价格（元/吨） | T56: -5 | U56: -30 | V56: -5 | W56: 600 | Z56: 液氨成本 | AA56: 万元 | AB56: =AB36*AB48 -> 0 | AC56: =AC36*AC48 -> 0 | AD56: =AD36*AD48 -> 0 | AE56: =AE36*AE48 -> 0 | AF56: =SUM(AB56:AE56) -> 0
A57: =AP270 -> 0 | B57: =$B$118 -> 褐煤3（云） | C57: =INDEX($B$111:$Q$131,MATCH($B57,$B$111:$B$131,0),MATCH(C$2,$B$111:$Q$111,0)) -> 3200 | D57: {=INDEX($B$111:$Q$131,MATCH($B57,$B$111:$B$131,0),COLUMN($D$2)-1)} -> 0.1333 | E57: =C57*D57 -> 426.56 | F57: =INDEX($B$111:$Q$131,MATCH($B57,$B$111:$B$131,0),MATCH(F$2,$B$111:$Q$111,0)) -> 19.15 | G57: =INDEX($B$111:$Q$131,MATCH($B57,$B$111:$B$131,0),MATCH(G$2,$B$111:$Q$111,0)) -> 23.873821 | H57: =INDEX($B$111:$Q$131,MATCH($B57,$B$111:$B$131,0),MATCH(H$2,$B$111:$Q$111,0)) -> 0.84706369 | I57: =INDEX($B$111:$Q$131,MATCH($B57,$B$111:$B$131,0),MATCH(I$2,$B$111:$Q$111,0)) -> 30.507667 | J57: =IFERROR(K57/K66*100,) -> 0 | K57: 0 | L57: {=LOOKUP(1,0/($B$111:$B$131=$B57),$L$111:$L$131)} -> 8 | M57: 0 | N57: =IF(P57>0,INDEX($B$111:$Z$131,MATCH(B57,$B$111:$B$131,0),MATCH($Z$111,$B$111:$Z$111,0))*C57*K57,C57*D57*K57) -> 0 | O57: =P57*K57 -> 0 | P57: {=INDEX($B$111:$AF$131,MATCH($B57,$B$111:$B$131,0),COLUMN($AA$111)-1)} -> 0 | Q57: =SUM(N57:O57) -> 0 | S57: 炉灰倒运单价（元/吨） | T57: 7.9 | U57: 30.92 | V57: 7.9 | W57: 0.9 | Z57: 炉灰倒运费 | AA57: 万元 | AB57: =AB30*AB42 -> 39.954197 | AC57: =AC30*AC42 -> 169.09756 | AD57: =AD30*AD42 -> 0 | AE57: =AE30*AE42 -> 0 | AF57: =SUM(AB57:AE57) -> 209.05176
A58: 自产比例（%） | B58: =$B$119 -> 褐煤32（港1） | C58: =INDEX($B$111:$Q$131,MATCH($B58,$B$111:$B$131,0),MATCH(C$2,$B$111:$Q$111,0)) -> 3200 | D58: {=INDEX($B$111:$Q$131,MATCH($B58,$B$111:$B$131,0),COLUMN($D$2)-1)} -> 0.1687875 | E58: =C58*D58 -> 540.12 | F58: =INDEX($B$111:$Q$131,MATCH($B58,$B$111:$B$131,0),MATCH(F$2,$B$111:$Q$111,0)) -> 32.112709 | G58: =INDEX($B$111:$Q$131,MATCH($B58,$B$111:$B$131,0),MATCH(G$2,$B$111:$Q$111,0)) -> 19.443643 | H58: =INDEX($B$111:$Q$131,MATCH($B58,$B$111:$B$131,0),MATCH(H$2,$B$111:$Q$111,0)) -> 0.77574029 | I58: =INDEX($B$111:$Q$131,MATCH($B58,$B$111:$B$131,0),MATCH(I$2,$B$111:$Q$111,0)) -> 24.82919 | J58: =IFERROR(K58/K66*100,) -> 0 | K58: 0 | L58: {=LOOKUP(1,0/($B$111:$B$131=$B58),$L$111:$L$131)} -> 100 | M58: 0 | N58: =IF(P58>0,INDEX($B$111:$Z$131,MATCH(B58,$B$111:$B$131,0),MATCH($Z$111,$B$111:$Z$111,0))*C58*K58,C58*D58*K58) -> 0 | O58: =P58*K58 -> 0 | P58: {=INDEX($B$111:$AF$131,MATCH($B58,$B$111:$B$131,0),COLUMN($AA$111)-1)} -> 95.32 | Q58: =SUM(N58:O58) -> 0 | S58: 炉渣倒运单价（元/吨） | T58: 7.9 | U58: 30.92 | V58: 7.9 | W58: 0.9 | Z58: 炉渣倒运费 | AA58: 万元 | AB58: =AB31*AB43 -> 54.93702 | AC58: =AC31*AC43 -> 10.627348 | AD58: =AD31*AD43 -> 0 | AE58: =AE31*AE43 -> 0 | AF58: =SUM(AB58:AE58) -> 65.564368
A59: =IFERROR((SUMIF($B$51:$B$65,$B$112,$K$51:$K$65)+SUMIF($B$51:$B$65,$B$113,$K$51:$K$65)+SUMIF($B$51:$B$65,$B$114,$K$51:$K$65)+SUMIF($B$51:$B$65,$B$115,$K$51:$K$65))/$K$66*100,) -> 0 | B59: =$B$120 -> 褐煤35（港2） | C59: =INDEX($B$111:$Q$131,MATCH($B59,$B$111:$B$131,0),MATCH(C$2,$B$111:$Q$111,0)) -> 3500 | D59: {=INDEX($B$111:$Q$131,MATCH($B59,$B$111:$B$131,0),COLUMN($D$2)-1)} -> 0.17313429 | E59: =C59*D59 -> 605.97 | F59: =INDEX($B$111:$Q$131,MATCH($B59,$B$111:$B$131,0),MATCH(F$2,$B$111:$Q$111,0)) -> 29.814059 | G59: =INDEX($B$111:$Q$131,MATCH($B59,$B$111:$B$131,0),MATCH(G$2,$B$111:$Q$111,0)) -> 17.717186 | H59: =INDEX($B$111:$Q$131,MATCH($B59,$B$111:$B$131,0),MATCH(H$2,$B$111:$Q$111,0)) -> 0.78167601 | I59: =INDEX($B$111:$Q$131,MATCH($B59,$B$111:$B$131,0),MATCH(I$2,$B$111:$Q$111,0)) -> 26.875931 | J59: =IFERROR(K59/K66*100,) -> 0 | K59: 0 | L59: {=LOOKUP(1,0/($B$111:$B$131=$B59),$L$111:$L$131)} -> 100 | M59: 0 | N59: =IF(P59>0,INDEX($B$111:$Z$131,MATCH(B59,$B$111:$B$131,0),MATCH($Z$111,$B$111:$Z$111,0))*C59*K59,C59*D59*K59) -> 0 | O59: =P59*K59 -> 0 | P59: {=INDEX($B$111:$AF$131,MATCH($B59,$B$111:$B$131,0),COLUMN($AA$111)-1)} -> 95.32 | Q59: =SUM(N59:O59) -> 0 | S59: 石膏倒运单价（元/吨） | T59: 7.9 | U59: 30.92 | V59: 7.9 | W59: 0 | Z59: 石膏倒运费 | AA59: 万元 | AB59: =AB32*AB44 -> 12.975013 | AC59: =AC32*AC44 -> 6.1969129 | AD59: =AD32*AD44 -> 0 | AE59: =AE32*AE44 -> 0 | AF59: =SUM(AB59:AE59) -> 19.171926
A60: 利润（万元） | B60: =$B$121 -> 褐煤38（港3） | C60: =INDEX($B$111:$Q$131,MATCH($B60,$B$111:$B$131,0),MATCH(C$2,$B$111:$Q$111,0)) -> 3800 | D60: {=INDEX($B$111:$Q$131,MATCH($B60,$B$111:$B$131,0),COLUMN($D$2)-1)} -> 0.16938421 | E60: =C60*D60 -> 643.66 | F60: =INDEX($B$111:$Q$131,MATCH($B60,$B$111:$B$131,0),MATCH(F$2,$B$111:$Q$111,0)) -> 34.679691 | G60: =INDEX($B$111:$Q$131,MATCH($B60,$B$111:$B$131,0),MATCH(G$2,$B$111:$Q$111,0)) -> 8.6727633 | H60: =INDEX($B$111:$Q$131,MATCH($B60,$B$111:$B$131,0),MATCH(H$2,$B$111:$Q$111,0)) -> 0.82970573 | I60: =INDEX($B$111:$Q$131,MATCH($B60,$B$111:$B$131,0),MATCH(I$2,$B$111:$Q$111,0)) -> 28.638706 | J60: =IFERROR(K60/K66*100,) -> 0 | K60: 0 | L60: {=LOOKUP(1,0/($B$111:$B$131=$B60),$L$111:$L$131)} -> 100 | M60: 0 | N60: =IF(P60>0,INDEX($B$111:$Z$131,MATCH(B60,$B$111:$B$131,0),MATCH($Z$111,$B$111:$Z$111,0))*C60*K60,C60*D60*K60) -> 0 | O60: =P60*K60 -> 0 | P60: {=INDEX($B$111:$AF$131,MATCH($B60,$B$111:$B$131,0),COLUMN($AA$111)-1)} -> 95.32 | Q60: =SUM(N60:O60) -> 0 | S60: 石粉/液氨单价（元/吨） | T60: 67 | U60: 86 | V60: 67 | W60: 2950
A61: =C107 -> -2190.1722 | B61: =$B$122 -> 褐煤46 | C61: =INDEX($B$111:$Q$131,MATCH($B61,$B$111:$B$131,0),MATCH(C$2,$B$111:$Q$111,0)) -> 4600 | D61: {=INDEX($B$111:$Q$131,MATCH($B61,$B$111:$B$131,0),COLUMN($D$2)-1)} -> 0.16142174 | E61: =C61*D61 -> 742.54 | F61: =INDEX($B$111:$Q$131,MATCH($B61,$B$111:$B$131,0),MATCH(F$2,$B$111:$Q$111,0)) -> 23.091665 | G61: =INDEX($B$111:$Q$131,MATCH($B61,$B$111:$B$131,0),MATCH(G$2,$B$111:$Q$111,0)) -> 10.878752 | H61: =INDEX($B$111:$Q$131,MATCH($B61,$B$111:$B$131,0),MATCH(H$2,$B$111:$Q$111,0)) -> 0.20812534 | I61: =INDEX($B$111:$Q$131,MATCH($B61,$B$111:$B$131,0),MATCH(I$2,$B$111:$Q$111,0)) -> 32.849465 | J61: =IFERROR(K61/K66*100,) -> 0 | K61: 0 | L61: {=LOOKUP(1,0/($B$111:$B$131=$B61),$L$111:$L$131)} -> 100 | M61: 0 | N61: =IF(P61>0,INDEX($B$111:$Z$131,MATCH(B61,$B$111:$B$131,0),MATCH($Z$111,$B$111:$Z$111,0))*C61*K61,C61*D61*K61) -> 0 | O61: =P61*K61 -> 0 | P61: {=INDEX($B$111:$AF$131,MATCH($B61,$B$111:$B$131,0),COLUMN($AA$111)-1)} -> 95.32 | Q61: =SUM(N61:O61) -> 0 | S61: 尿素单价（元/吨） | T61: 2200 | U61: 2500 | V61: 0 | W61: 0
A62: 锅炉效率（%） | B62: =$B$123 -> 烟煤55 | C62: =INDEX($B$111:$Q$131,MATCH($B62,$B$111:$B$131,0),MATCH(C$2,$B$111:$Q$111,0)) -> 5500 | D62: {=INDEX($B$111:$Q$131,MATCH($B62,$B$111:$B$131,0),COLUMN($D$2)-1)} -> 0.16633091 | E62: =C62*D62 -> 914.82 | F62: =INDEX($B$111:$Q$131,MATCH($B62,$B$111:$B$131,0),MATCH(F$2,$B$111:$Q$111,0)) -> 10.316451 | G62: =INDEX($B$111:$Q$131,MATCH($B62,$B$111:$B$131,0),MATCH(G$2,$B$111:$Q$111,0)) -> 19.875802 | H62: =INDEX($B$111:$Q$131,MATCH($B62,$B$111:$B$131,0),MATCH(H$2,$B$111:$Q$111,0)) -> 0.47663777 | I62: =INDEX($B$111:$Q$131,MATCH($B62,$B$111:$B$131,0),MATCH(I$2,$B$111:$Q$111,0)) -> 25.313893 | J62: =IFERROR(K62/K66*100,) -> 0 | K62: 0 | L62: {=LOOKUP(1,0/($B$111:$B$131=$B62),$L$111:$L$131)} -> 100 | M62: 0 | N62: =IF(P62>0,INDEX($B$111:$Z$131,MATCH(B62,$B$111:$B$131,0),MATCH($Z$111,$B$111:$Z$111,0))*C62*K62,C62*D62*K62) -> 0 | O62: =P62*K62 -> 0 | P62: {=INDEX($B$111:$AF$131,MATCH($B62,$B$111:$B$131,0),COLUMN($AA$111)-1)} -> 95.32 | Q62: =SUM(N62:O62) -> 0 | S62: 销售蒸汽（万吨） | T62: 0 | U62: 0 | V62: 0 | W62: 0
A63: =AP271*100 -> 0 | B63: =$B$124 -> 烟煤50备 | C63: =INDEX($B$111:$Q$131,MATCH($B63,$B$111:$B$131,0),MATCH(C$2,$B$111:$Q$111,0)) -> 5000 | D63: {=INDEX($B$111:$Q$131,MATCH($B63,$B$111:$B$131,0),COLUMN($D$2)-1)} -> 0 | E63: =C63*D63 -> 0 | F63: =INDEX($B$111:$Q$131,MATCH($B63,$B$111:$B$131,0),MATCH(F$2,$B$111:$Q$111,0)) -> 0 | G63: =INDEX($B$111:$Q$131,MATCH($B63,$B$111:$B$131,0),MATCH(G$2,$B$111:$Q$111,0)) -> 0 | H63: =INDEX($B$111:$Q$131,MATCH($B63,$B$111:$B$131,0),MATCH(H$2,$B$111:$Q$111,0)) -> 0 | I63: =INDEX($B$111:$Q$131,MATCH($B63,$B$111:$B$131,0),MATCH(I$2,$B$111:$Q$111,0)) -> 0 | J63: =IFERROR(K63/K66*100,) -> 0 | K63: 0 | L63: {=LOOKUP(1,0/($B$111:$B$131=$B63),$L$111:$L$131)} -> 0 | M63: 0 | N63: =IF(P63>0,INDEX($B$111:$Z$131,MATCH(B63,$B$111:$B$131,0),MATCH($Z$111,$B$111:$Z$111,0))*C63*K63,C63*D63*K63) -> 0 | O63: =P63*K63 -> 0 | P63: {=INDEX($B$111:$AF$131,MATCH($B63,$B$111:$B$131,0),COLUMN($AA$111)-1)} -> 0 | Q63: =SUM(N63:O63) -> 0 | S63: 蒸汽单价（元/吨） | T63: 168 | U63: 168 | V63: 168 | W63: 168
A64: 汽机热耗率 | B64: =$B$125 -> 烟煤55备 | C64: =INDEX($B$111:$Q$131,MATCH($B64,$B$111:$B$131,0),MATCH(C$2,$B$111:$Q$111,0)) -> 5500 | D64: {=INDEX($B$111:$Q$131,MATCH($B64,$B$111:$B$131,0),COLUMN($D$2)-1)} -> 0 | E64: =C64*D64 -> 0 | F64: =INDEX($B$111:$Q$131,MATCH($B64,$B$111:$B$131,0),MATCH(F$2,$B$111:$Q$111,0)) -> 0 | G64: =INDEX($B$111:$Q$131,MATCH($B64,$B$111:$B$131,0),MATCH(G$2,$B$111:$Q$111,0)) -> 0 | H64: =INDEX($B$111:$Q$131,MATCH($B64,$B$111:$B$131,0),MATCH(H$2,$B$111:$Q$111,0)) -> 0 | I64: =INDEX($B$111:$Q$131,MATCH($B64,$B$111:$B$131,0),MATCH(I$2,$B$111:$Q$111,0)) -> 0 | J64: =IFERROR(K64/K66*100,) -> 0 | K64: 0 | L64: {=LOOKUP(1,0/($B$111:$B$131=$B64),$L$111:$L$131)} -> 0 | M64: 0 | N64: =IF(P64>0,INDEX($B$111:$Z$131,MATCH(B64,$B$111:$B$131,0),MATCH($Z$111,$B$111:$Z$111,0))*C64*K64,C64*D64*K64) -> 0 | O64: =P64*K64 -> 0 | P64: {=INDEX($B$111:$AF$131,MATCH($B64,$B$111:$B$131,0),COLUMN($AA$111)-1)} -> 0 | Q64: =SUM(N64:O64) -> 0 | S64: 炉灰调湿比例% | T64: 25 | U64: 25 | V64: 25 | W64: 20
A65: =AP272 -> 0 | B65: =$B$127 -> 石油焦 | C65: =INDEX($B$111:$Q$131,MATCH($B65,$B$111:$B$131,0),MATCH(C$2,$B$111:$Q$111,0)) -> 7256.4478 | D65: {=INDEX($B$111:$Q$131,MATCH($B65,$B$111:$B$131,0),COLUMN($D$2)-1)} -> 0 | E65: =C65*D65 -> 0 | F65: =INDEX($B$111:$Q$131,MATCH($B65,$B$111:$B$131,0),MATCH(F$2,$B$111:$Q$111,0)) -> 0 | G65: =INDEX($B$111:$Q$131,MATCH($B65,$B$111:$B$131,0),MATCH(G$2,$B$111:$Q$111,0)) -> 0 | H65: =INDEX($B$111:$Q$131,MATCH($B65,$B$111:$B$131,0),MATCH(H$2,$B$111:$Q$111,0)) -> 0 | I65: =INDEX($B$111:$Q$131,MATCH($B65,$B$111:$B$131,0),MATCH(I$2,$B$111:$Q$111,0)) -> 0 | J65: =IFERROR(K65/K66*100,) -> 0 | K65: 0 | L65: {=LOOKUP(1,0/($B$111:$B$131=$B65),$L$111:$L$131)} -> 0 | M65: 0 | N65: =IF(P65>0,INDEX($B$111:$Z$131,MATCH(B65,$B$111:$B$131,0),MATCH($Z$111,$B$111:$Z$111,0))*C65*K65,C65*D65*K65) -> 0 | O65: =P65*K65 -> 0 | P65: {=INDEX($B$111:$AF$131,MATCH($B65,$B$111:$B$131,0),COLUMN($AA$111)-1)} -> 0 | Q65: =SUM(N65:O65) -> 0 | S65: 炉渣调湿比例% | T65: 25 | U65: 25 | V65: 25 | W65: 35
B66: 加权平均 | C66: =IFERROR(SUMPRODUCT(C51:C65,K51:K65)/SUM(K51:K65),) -> 0 | D66: =IFERROR(SUMPRODUCT(C51:C65,D51:D65,K51:K65)/SUMPRODUCT(C51:C65,K51:K65),) -> 0 | E66: =IFERROR(SUMPRODUCT(C51:C65,E51:E65,K51:K65)/SUMPRODUCT(C51:C65,K51:K65),) -> 0 | F66: =IFERROR(SUMPRODUCT(F51:F65,K51:K65)/SUM(K51:K65),) -> 0 | G66: =IFERROR(SUMPRODUCT(G51:G65,K51:K65)/SUM(K51:K65),) -> 0 | H66: =IFERROR(SUMPRODUCT(H51:H65,K51:K65)/SUM(K51:K65),) -> 0 | I66: =IFERROR(SUMPRODUCT(I51:I65,K51:K65)/SUM(K51:K65),) -> 0 | J66: =IFERROR(SUM(J51:J65),) -> 0 | K66: =IFERROR(SUM(K51:K65),) -> 0 | L66: =SUM(L51:L65) -> 534.85412 | M66: =SUM(M51:M65) -> 0 | N66: =SUM(N51:N65) -> 0 | O66: =SUM(O51:O65) -> 0 | P66: =IFERROR(SUMPRODUCT(P51:P65,K51:K65)/SUM(K51:K65),) -> 0 | Q66: =SUM(Q51:Q65) -> 0 | R66: =SUM(R51:R65) -> 0 | S66: 石油焦燃烬率% | T66: 85 | U66: 85 | V66: 85 | W66: 85
B67: 炉灰占比% | C67: =V$47 -> 60 | D67: 炉灰产量（万吨） | E67: =$K66*$G66/100*C67/100 -> 0 | F67: 炉灰销售% | G67: =V$51 -> 5 | H67: 炉灰销量（万吨） | I67: =E67*G67/100 -> 0 | J67: 炉灰价格（元/吨） | K67: =V$54 -> -20 | L67: 炉灰收入（万元） | M67: =I67*K67 -> 0 | N67: 炉灰税率% | O67: 13 | P67: 税后金额（万元） | Q67: =M67/(1+O67/100) -> 0
B68: 炉渣占比% | C68: =100-C67 -> 40 | D68: 炉渣产量（万吨） | E68: =$K66*$G66/100*C68/100 -> 0 | F68: 炉渣销售% | G68: =V$52 -> 40 | H68: 炉渣销量（万吨） | I68: =E68*G68/100 -> 0 | J68: 炉渣价格（元/吨） | K68: =V$55 -> -8 | L68: 炉渣收入（万元） | M68: =I68*K68 -> 0 | N68: 炉渣税率% | O68: 13 | P68: 税后金额（万元） | Q68: =M68/(1+O68/100) -> 0
B69: 钙硫比 | C69: =V$49 -> 4.35 | D69: 石膏产量（万吨） | E69: =C70*I73 -> 0 | F69: 石膏销售% | G69: =V$53 -> 40 | H69: 石膏销量（万吨） | I69: =E69*G69/100 -> 0 | J69: 石膏价格（元/吨） | K69: =V$56 -> -5 | L69: 石膏收入（万元） | M69: =I69*K69 -> 0 | N69: 硫酸铵税率% | O69: 13 | P69: 税后金额（万元） | Q69: =M69/(1+O69/100) -> 0
B70: 石膏石粉比 | C70: =V$50 -> 1.7 | D70: 销售蒸汽（万吨） | E70: =V$62 -> 0 | F70: 炉灰调湿比例% | G70: =V64 -> 25 | H70: 炉灰倒运量（万吨） | I70: =(E67-I67)/(1-G70/100) -> 0 | J70: 炉灰倒运单价（元/吨） | K70: =V$57 -> 7.9 | L70: 炉灰倒运费（万元） | M70: =I70*K70 -> 0 | N70: 炉灰倒运税率% | O70: 6 | P70: 税后金额（万元） | Q70: =M70/(1+O70/100) -> 0
D71: 蒸汽单价（元/吨） | E71: =V$63 -> 168 | F71: 炉渣调湿比例% | G71: =V65 -> 25 | H71: 炉渣倒运量（万吨） | I71: =(E68-I68)/(1-G71/100) -> 0 | J71: 炉渣倒运单价（元/吨） | K71: =V$58 -> 7.9 | L71: 炉渣倒运费（万元） | M71: =I71*K71 -> 0 | N71: 炉渣倒运税率% | O71: 6 | P71: 税后金额（万元） | Q71: =M71/(1+O71/100) -> 0
D72: 蒸汽收入（万元） | E72: =E70*E71 -> 0 | H72: 石膏倒运量（万吨） | I72: =E69-I69 -> 0 | J72: 石膏倒运单价（元/吨） | K72: =V$59 -> 7.9 | L72: 石膏倒运费（万元） | M72: =I72*K72 -> 0 | N72: 石膏运税率% | O72: 6 | P72: 税后金额（万元） | Q72: =M72/(1+O72/100) -> 0
D73: 税率% | E73: 9 | H73: 石粉耗用（万吨） | I73: =H66/100*K66*C69 -> 0 | J73: 石粉单价（元/吨） | K73: =V$60 -> 67 | L73: 石粉费用（万元） | M73: =I73*K73 -> 0 | N73: 石粉税率% | O73: 13 | P73: 税后金额（万元） | Q73: =M73/(1+O73/100) -> 0
D74: 税后蒸汽收入（万元） | E74: =E72/(1+E73/100) -> 0 | H74: 尿素耗用（万吨） | I74: =(0.016*I66+0.09)/100*K66*12%/85%*2.354*0 -> 0 | J74: 尿素单价（元/吨） | K74: =V$61 -> 0 | L74: 尿素费用（万元） | M74: =I74*K74 -> 0 | N74: 尿素税率% | O74: 13 | P74: 税后金额（万元） | Q74: =M74/(1+O74/100) -> 0
A75: 田东 | B75: =$B$112 -> 东怀 | C75: =INDEX($B$111:$Q$131,MATCH($B75,$B$111:$B$131,0),MATCH(C$2,$B$111:$Q$111,0)) -> 2482.3501 | D75: {=INDEX($B$111:$Q$131,MATCH($B75,$B$111:$B$131,0),COLUMN($D$2)+1)} -> 0.12292394 | E75: =C75*D75 -> 305.14026 | F75: =INDEX($B$111:$Q$131,MATCH($B75,$B$111:$B$131,0),MATCH(F$2,$B$111:$Q$111,0)) -> 9.05 | G75: =INDEX($B$111:$Q$131,MATCH($B75,$B$111:$B$131,0),MATCH(G$2,$B$111:$Q$111,0)) -> 53.753421 | H75: =INDEX($B$111:$Q$131,MATCH($B75,$B$111:$B$131,0),MATCH(H$2,$B$111:$Q$111,0)) -> 1.5392982 | I75: =INDEX($B$111:$Q$131,MATCH($B75,$B$111:$B$131,0),MATCH(I$2,$B$111:$Q$111,0)) -> 20.240833 | J75: =IFERROR(K75/K90*100,) -> 0 | K75: 0 | L75: {=LOOKUP(1,0/($B$111:$B$131=$B75),$L$111:$L$131)} -> 16.550016 | M75: 0 | N75: =IF(P75>0,INDEX($B$111:$Z$131,MATCH(B75,$B$111:$B$131,0),MATCH($Z$111,$B$111:$Z$111,0))*C75*K75,C75*D75*K75) -> 0 | O75: =P75*K75 -> 0 | P75: {=INDEX($B$111:$AF$131,MATCH($B75,$B$111:$B$131,0),COLUMN($AA$111)+1)} -> 19.67 | Q75: =SUM(N75:O75) -> 0
A76: 发电量 | B76: =$B$113 -> 跃进 | C76: =INDEX($B$111:$Q$131,MATCH($B76,$B$111:$B$131,0),MATCH(C$2,$B$111:$Q$111,0)) -> 1800 | D76: {=INDEX($B$111:$Q$131,MATCH($B76,$B$111:$B$131,0),COLUMN($D$2)+1)} -> 0.11555 | E76: =C76*D76 -> 207.99 | F76: =INDEX($B$111:$Q$131,MATCH($B76,$B$111:$B$131,0),MATCH(F$2,$B$111:$Q$111,0)) -> 9.9 | G76: =INDEX($B$111:$Q$131,MATCH($B76,$B$111:$B$131,0),MATCH(G$2,$B$111:$Q$111,0)) -> 59.606917 | H76: =INDEX($B$111:$Q$131,MATCH($B76,$B$111:$B$131,0),MATCH(H$2,$B$111:$Q$111,0)) -> 0.41611229 | I76: =INDEX($B$111:$Q$131,MATCH($B76,$B$111:$B$131,0),MATCH(I$2,$B$111:$Q$111,0)) -> 16.798781 | J76: =IFERROR(K76/K90*100,) -> 0 | K76: 0 | L76: 0 | M76: 0 | N76: =IF(P76>0,INDEX($B$111:$Z$131,MATCH(B76,$B$111:$B$131,0),MATCH($Z$111,$B$111:$Z$111,0))*C76*K76,C76*D76*K76) -> 0 | O76: =P76*K76 -> 0 | P76: {=INDEX($B$111:$AF$131,MATCH($B76,$B$111:$B$131,0),COLUMN($AA$111)+1)} -> 9.99 | Q76: =SUM(N76:O76) -> 0
A77: =AP343 -> 0 | B77: =$B$114 -> 州景 | C77: =INDEX($B$111:$Q$131,MATCH($B77,$B$111:$B$131,0),MATCH(C$2,$B$111:$Q$111,0)) -> 0 | D77: {=INDEX($B$111:$Q$131,MATCH($B77,$B$111:$B$131,0),COLUMN($D$2)+1)} -> 0 | E77: =C77*D77 -> 0 | F77: =INDEX($B$111:$Q$131,MATCH($B77,$B$111:$B$131,0),MATCH(F$2,$B$111:$Q$111,0)) -> 15.681 | G77: =INDEX($B$111:$Q$131,MATCH($B77,$B$111:$B$131,0),MATCH(G$2,$B$111:$Q$111,0)) -> 65.22 | H77: =INDEX($B$111:$Q$131,MATCH($B77,$B$111:$B$131,0),MATCH(H$2,$B$111:$Q$111,0)) -> 0.63 | I77: =INDEX($B$111:$Q$131,MATCH($B77,$B$111:$B$131,0),MATCH(I$2,$B$111:$Q$111,0)) -> 58.6 | J77: =IFERROR(K77/K90*100,) -> 0 | K77: 0 | L77: {=LOOKUP(1,0/($B$111:$B$131=$B77),$L$111:$L$131)} -> 0 | M77: 0 | N77: =IF(P77>0,INDEX($B$111:$Z$131,MATCH(B77,$B$111:$B$131,0),MATCH($Z$111,$B$111:$Z$111,0))*C77*K77,C77*D77*K77) -> 0 | O77: =P77*K77 -> 0 | P77: {=INDEX($B$111:$AF$131,MATCH($B77,$B$111:$B$131,0),COLUMN($AA$111)+1)} -> 6.01 | Q77: =SUM(N77:O77) -> 0
A78: 综合厂用电率 | B78: =$B$115 -> 那荷 | C78: =INDEX($B$111:$Q$131,MATCH($B78,$B$111:$B$131,0),MATCH(C$2,$B$111:$Q$111,0)) -> 0 | D78: {=INDEX($B$111:$Q$131,MATCH($B78,$B$111:$B$131,0),COLUMN($D$2)+1)} -> 0 | E78: =C78*D78 -> 0 | F78: =INDEX($B$111:$Q$131,MATCH($B78,$B$111:$B$131,0),MATCH(F$2,$B$111:$Q$111,0)) -> 8.93 | G78: =INDEX($B$111:$Q$131,MATCH($B78,$B$111:$B$131,0),MATCH(G$2,$B$111:$Q$111,0)) -> 71.46 | H78: =INDEX($B$111:$Q$131,MATCH($B78,$B$111:$B$131,0),MATCH(H$2,$B$111:$Q$111,0)) -> 0.34 | I78: =INDEX($B$111:$Q$131,MATCH($B78,$B$111:$B$131,0),MATCH(I$2,$B$111:$Q$111,0)) -> 56.85 | J78: =IFERROR(K78/K90*100,) -> 0 | K78: 0 | L78: 0 | M78: 0 | N78: =IF(P78>0,INDEX($B$111:$Z$131,MATCH(B78,$B$111:$B$131,0),MATCH($Z$111,$B$111:$Z$111,0))*C78*K78,C78*D78*K78) -> 0 | O78: =P78*K78 -> 0 | P78: {=INDEX($B$111:$AF$131,MATCH($B78,$B$111:$B$131,0),COLUMN($AA$111)+1)} -> 13.9 | Q78: =SUM(N78:O78) -> 0
A79: 8.8606779 | B79: =$B$116 -> 褐煤2（云）长协 | C79: =INDEX($B$111:$Q$131,MATCH($B79,$B$111:$B$131,0),MATCH(C$2,$B$111:$Q$111,0)) -> 2400 | D79: {=INDEX($B$111:$Q$131,MATCH($B79,$B$111:$B$131,0),COLUMN($D$2)+1)} -> 0.123 | E79: =C79*D79 -> 295.2 | F79: =INDEX($B$111:$Q$131,MATCH($B79,$B$111:$B$131,0),MATCH(F$2,$B$111:$Q$111,0)) -> 19.2 | G79: =INDEX($B$111:$Q$131,MATCH($B79,$B$111:$B$131,0),MATCH(G$2,$B$111:$Q$111,0)) -> 32.974564 | H79: =INDEX($B$111:$Q$131,MATCH($B79,$B$111:$B$131,0),MATCH(H$2,$B$111:$Q$111,0)) -> 0.80500871 | I79: =INDEX($B$111:$Q$131,MATCH($B79,$B$111:$B$131,0),MATCH(I$2,$B$111:$Q$111,0)) -> 28.483232 | J79: =IFERROR(K79/K90*100,) -> 0 | K79: 0 | L79: 0 | M79: 0 | N79: =IF(P79>0,INDEX($B$111:$Z$131,MATCH(B79,$B$111:$B$131,0),MATCH($Z$111,$B$111:$Z$111,0))*C79*K79,C79*D79*K79) -> 0 | O79: =P79*K79 -> 0 | P79: {=INDEX($B$111:$AF$131,MATCH($B79,$B$111:$B$131,0),COLUMN($AA$111)+1)} -> 0 | Q79: =SUM(N79:O79) -> 0
A80: 发电标煤耗 | B80: =$B$117 -> 褐煤3（云）长协 | C80: =INDEX($B$111:$Q$131,MATCH($B80,$B$111:$B$131,0),MATCH(C$2,$B$111:$Q$111,0)) -> 3200 | D80: {=INDEX($B$111:$Q$131,MATCH($B80,$B$111:$B$131,0),COLUMN($D$2)+1)} -> 0.133 | E80: =C80*D80 -> 425.6 | F80: =INDEX($B$111:$Q$131,MATCH($B80,$B$111:$B$131,0),MATCH(F$2,$B$111:$Q$111,0)) -> 19.15 | G80: =INDEX($B$111:$Q$131,MATCH($B80,$B$111:$B$131,0),MATCH(G$2,$B$111:$Q$111,0)) -> 23.873821 | H80: =INDEX($B$111:$Q$131,MATCH($B80,$B$111:$B$131,0),MATCH(H$2,$B$111:$Q$111,0)) -> 0.84706369 | I80: =INDEX($B$111:$Q$131,MATCH($B80,$B$111:$B$131,0),MATCH(I$2,$B$111:$Q$111,0)) -> 30.507667 | J80: =IFERROR(K80/K90*100,) -> 0 | K80: 0 | L80: 0 | M80: 0 | N80: =IF(P80>0,INDEX($B$111:$Z$131,MATCH(B80,$B$111:$B$131,0),MATCH($Z$111,$B$111:$Z$111,0))*C80*K80,C80*D80*K80) -> 0 | O80: =P80*K80 -> 0 | P80: {=INDEX($B$111:$AF$131,MATCH($B80,$B$111:$B$131,0),COLUMN($AA$111)+1)} -> 0 | Q80: =SUM(N80:O80) -> 0 | X80: =[3]采购参数!A1 -> 2023年10月至2024年12月煤炭采购参数
A81: =AP336 -> 0 | B81: =$B$118 -> 褐煤3（云） | C81: =INDEX($B$111:$Q$131,MATCH($B81,$B$111:$B$131,0),MATCH(C$2,$B$111:$Q$111,0)) -> 3200 | D81: {=INDEX($B$111:$Q$131,MATCH($B81,$B$111:$B$131,0),COLUMN($D$2)+1)} -> 0.1333 | E81: =C81*D81 -> 426.56 | F81: =INDEX($B$111:$Q$131,MATCH($B81,$B$111:$B$131,0),MATCH(F$2,$B$111:$Q$111,0)) -> 19.15 | G81: =INDEX($B$111:$Q$131,MATCH($B81,$B$111:$B$131,0),MATCH(G$2,$B$111:$Q$111,0)) -> 23.873821 | H81: =INDEX($B$111:$Q$131,MATCH($B81,$B$111:$B$131,0),MATCH(H$2,$B$111:$Q$111,0)) -> 0.84706369 | I81: =INDEX($B$111:$Q$131,MATCH($B81,$B$111:$B$131,0),MATCH(I$2,$B$111:$Q$111,0)) -> 30.507667 | J81: =IFERROR(K81/K90*100,) -> 0 | K81: 0 | L81: {=LOOKUP(1,0/($B$111:$B$131=$B81),$L$111:$L$131)} -> 8 | M81: 0 | N81: =IF(P81>0,INDEX($B$111:$Z$131,MATCH(B81,$B$111:$B$131,0),MATCH($Z$111,$B$111:$Z$111,0))*C81*K81,C81*D81*K81) -> 0 | O81: =P81*K81 -> 0 | P81: {=INDEX($B$111:$AF$131,MATCH($B81,$B$111:$B$131,0),COLUMN($AA$111)+1)} -> 0 | Q81: =SUM(N81:O81) -> 0 | X81: =[3]采购参数!A2 -> 田东 | AD81: =[3]采购参数!G2 -> 百矿、银海、德保
A82: 自产比例（%） | B82: =$B$119 -> 褐煤32（港1） | C82: =INDEX($B$111:$Q$131,MATCH($B82,$B$111:$B$131,0),MATCH(C$2,$B$111:$Q$111,0)) -> 3200 | D82: {=INDEX($B$111:$Q$131,MATCH($B82,$B$111:$B$131,0),COLUMN($D$2)+1)} -> 0.165975 | E82: =C82*D82 -> 531.12 | F82: =INDEX($B$111:$Q$131,MATCH($B82,$B$111:$B$131,0),MATCH(F$2,$B$111:$Q$111,0)) -> 32.112709 | G82: =INDEX($B$111:$Q$131,MATCH($B82,$B$111:$B$131,0),MATCH(G$2,$B$111:$Q$111,0)) -> 19.443643 | H82: =INDEX($B$111:$Q$131,MATCH($B82,$B$111:$B$131,0),MATCH(H$2,$B$111:$Q$111,0)) -> 0.77574029 | I82: =INDEX($B$111:$Q$131,MATCH($B82,$B$111:$B$131,0),MATCH(I$2,$B$111:$Q$111,0)) -> 24.82919 | J82: =IFERROR(K82/K90*100,) -> 0 | K82: 0 | L82: {=LOOKUP(1,0/($B$111:$B$131=$B82),$L$111:$L$131)} -> 100 | M82: 0 | N82: =IF(P82>0,INDEX($B$111:$Z$131,MATCH(B82,$B$111:$B$131,0),MATCH($Z$111,$B$111:$Z$111,0))*C82*K82,C82*D82*K82) -> 0 | O82: =P82*K82 -> 0 | P82: {=INDEX($B$111:$AF$131,MATCH($B82,$B$111:$B$131,0),COLUMN($AA$111)+1)} -> 86.32 | Q82: =SUM(N82:O82) -> 0 | X82: =[3]采购参数!A3 -> 煤种 | Y82: 热值 | Z82: 水分% | AA82: 灰分% | AB82: 硫分% | AC82: 挥发分% | AD82: 煤种 | AE82: 热值 | AF82: 水分% | AG82: 灰分% | AH82: 硫分% | AI82: 挥发分%
A83: =IFERROR((SUMIF($B$75:$B$89,$B$112,$K$75:$K$89)+SUMIF($B$75:$B$89,$B$113,$K$75:$K$89)+SUMIF($B$75:$B$89,$B$114,$K$75:$K$89)+SUMIF($B$75:$B$89,$B$115,$K$75:$K$89))/$K$90*100,) -> 0 | B83: =$B$120 -> 褐煤35（港2） | C83: =INDEX($B$111:$Q$131,MATCH($B83,$B$111:$B$131,0),MATCH(C$2,$B$111:$Q$111,0)) -> 3500 | D83: {=INDEX($B$111:$Q$131,MATCH($B83,$B$111:$B$131,0),COLUMN($D$2)+1)} -> 0.17056286 | E83: =C83*D83 -> 596.97 | F83: =INDEX($B$111:$Q$131,MATCH($B83,$B$111:$B$131,0),MATCH(F$2,$B$111:$Q$111,0)) -> 29.814059 | G83: =INDEX($B$111:$Q$131,MATCH($B83,$B$111:$B$131,0),MATCH(G$2,$B$111:$Q$111,0)) -> 17.717186 | H83: =INDEX($B$111:$Q$131,MATCH($B83,$B$111:$B$131,0),MATCH(H$2,$B$111:$Q$111,0)) -> 0.78167601 | I83: =INDEX($B$111:$Q$131,MATCH($B83,$B$111:$B$131,0),MATCH(I$2,$B$111:$Q$111,0)) -> 26.875931 | J83: =IFERROR(K83/K90*100,) -> 0 | K83: 0 | L83: {=LOOKUP(1,0/($B$111:$B$131=$B83),$L$111:$L$131)} -> 100 | M83: 0 | N83: =IF(P83>0,INDEX($B$111:$Z$131,MATCH(B83,$B$111:$B$131,0),MATCH($Z$111,$B$111:$Z$111,0))*C83*K83,C83*D83*K83) -> 0 | O83: =P83*K83 -> 0 | P83: {=INDEX($B$111:$AF$131,MATCH($B83,$B$111:$B$131,0),COLUMN($AA$111)+1)} -> 86.32 | Q83: =SUM(N83:O83) -> 0 | X83: =[3]采购参数!A4 -> 东怀 | Y83: =[3]采购参数!B4 -> 2349.9773 | Z83: =[3]采购参数!C4 -> 8.68 | AA83: =[3]采购参数!D4 -> 51.35 | AB83: =[3]采购参数!E4 -> 0.83497432 | AC83: =[3]采购参数!F4 -> 55 | AD83: =[3]采购参数!G4 -> 东怀 | AE83: =[3]采购参数!H4 -> 2349.9773 | ... AI83: =[3]采购参数!L4 -> 55
A84: 利润（万元） | B84: =$B$121 -> 褐煤38（港3） | C84: =INDEX($B$111:$Q$131,MATCH($B84,$B$111:$B$131,0),MATCH(C$2,$B$111:$Q$111,0)) -> 3800 | D84: {=INDEX($B$111:$Q$131,MATCH($B84,$B$111:$B$131,0),COLUMN($D$2)+1)} -> 0.16701579 | E84: =C84*D84 -> 634.66 | F84: =INDEX($B$111:$Q$131,MATCH($B84,$B$111:$B$131,0),MATCH(F$2,$B$111:$Q$111,0)) -> 34.679691 | G84: =INDEX($B$111:$Q$131,MATCH($B84,$B$111:$B$131,0),MATCH(G$2,$B$111:$Q$111,0)) -> 8.6727633 | H84: =INDEX($B$111:$Q$131,MATCH($B84,$B$111:$B$131,0),MATCH(H$2,$B$111:$Q$111,0)) -> 0.82970573 | I84: =INDEX($B$111:$Q$131,MATCH($B84,$B$111:$B$131,0),MATCH(I$2,$B$111:$Q$111,0)) -> 28.638706 | J84: =IFERROR(K84/K90*100,) -> 0 | K84: 0 | L84: {=LOOKUP(1,0/($B$111:$B$131=$B84),$L$111:$L$131)} -> 100 | M84: 0 | N84: =IF(P84>0,INDEX($B$111:$Z$131,MATCH(B84,$B$111:$B$131,0),MATCH($Z$111,$B$111:$Z$111,0))*C84*K84,C84*D84*K84) -> 0 | O84: =P84*K84 -> 0 | P84: {=INDEX($B$111:$AF$131,MATCH($B84,$B$111:$B$131,0),COLUMN($AA$111)+1)} -> 86.32 | Q84: =SUM(N84:O84) -> 0 | X84: =[3]采购参数!A5 -> 跃进 | Y84: =[3]采购参数!B5 -> 1650.068 | Z84: =[3]采购参数!C5 -> 9.3621271 | AA84: =[3]采购参数!D5 -> 61.227066 | AB84: =[3]采购参数!E5 -> 0.35969192 | AC84: =[3]采购参数!F5 -> 55 | AD84: =[3]采购参数!G5 -> 跃进 | AE84: =[3]采购参数!H5 -> 1650.068 | ... AI84: =[3]采购参数!L5 -> 55
A85: =C108 -> -1038.5816 | B85: =$B$122 -> 褐煤46 | C85: =INDEX($B$111:$Q$131,MATCH($B85,$B$111:$B$131,0),MATCH(C$2,$B$111:$Q$111,0)) -> 4600 | D85: {=INDEX($B$111:$Q$131,MATCH($B85,$B$111:$B$131,0),COLUMN($D$2)+1)} -> 0.15946522 | E85: =C85*D85 -> 733.54 | F85: =INDEX($B$111:$Q$131,MATCH($B85,$B$111:$B$131,0),MATCH(F$2,$B$111:$Q$111,0)) -> 23.091665 | G85: =INDEX($B$111:$Q$131,MATCH($B85,$B$111:$B$131,0),MATCH(G$2,$B$111:$Q$111,0)) -> 10.878752 | H85: =INDEX($B$111:$Q$131,MATCH($B85,$B$111:$B$131,0),MATCH(H$2,$B$111:$Q$111,0)) -> 0.20812534 | I85: =INDEX($B$111:$Q$131,MATCH($B85,$B$111:$B$131,0),MATCH(I$2,$B$111:$Q$111,0)) -> 32.849465 | J85: =IFERROR(K85/K90*100,) -> 0 | K85: 0 | L85: {=LOOKUP(1,0/($B$111:$B$131=$B85),$L$111:$L$131)} -> 100 | M85: 0 | N85: =IF(P85>0,INDEX($B$111:$Z$131,MATCH(B85,$B$111:$B$131,0),MATCH($Z$111,$B$111:$Z$111,0))*C85*K85,C85*D85*K85) -> 0 | O85: =P85*K85 -> 0 | P85: {=INDEX($B$111:$AF$131,MATCH($B85,$B$111:$B$131,0),COLUMN($AA$111)+1)} -> 86.32 | Q85: =SUM(N85:O85) -> 0 | X85: =[3]采购参数!A6 -> 州景 | Y85: =[3]采购参数!B6 -> 1749.9667 | Z85: =[3]采购参数!C6 -> 11.74789 | AA85: =[3]采购参数!D6 -> 53.715896 | AB85: =[3]采购参数!E6 -> 0.5293873 | AC85: =[3]采购参数!F6 -> 55 | AD85: =[3]采购参数!G6 -> 州景 | AE85: =[3]采购参数!H6 -> 1749.9667 | ... AI85: =[3]采购参数!L6 -> 55
A86: 锅炉效率（%） | B86: =$B$123 -> 烟煤55 | C86: =INDEX($B$111:$Q$131,MATCH($B86,$B$111:$B$131,0),MATCH(C$2,$B$111:$Q$111,0)) -> 5500 | D86: {=INDEX($B$111:$Q$131,MATCH($B86,$B$111:$B$131,0),COLUMN($D$2)+1)} -> 0.16469455 | E86: =C86*D86 -> 905.82 | F86: =INDEX($B$111:$Q$131,MATCH($B86,$B$111:$B$131,0),MATCH(F$2,$B$111:$Q$111,0)) -> 10.316451 | G86: =INDEX($B$111:$Q$131,MATCH($B86,$B$111:$B$131,0),MATCH(G$2,$B$111:$Q$111,0)) -> 19.875802 | H86: =INDEX($B$111:$Q$131,MATCH($B86,$B$111:$B$131,0),MATCH(H$2,$B$111:$Q$111,0)) -> 0.47663777 | I86: =INDEX($B$111:$Q$131,MATCH($B86,$B$111:$B$131,0),MATCH(I$2,$B$111:$Q$111,0)) -> 25.313893 | J86: =IFERROR(K86/K90*100,) -> 0 | K86: 0 | L86: {=LOOKUP(1,0/($B$111:$B$131=$B86),$L$111:$L$131)} -> 100 | M86: 0 | N86: =IF(P86>0,INDEX($B$111:$Z$131,MATCH(B86,$B$111:$B$131,0),MATCH($Z$111,$B$111:$Z$111,0))*C86*K86,C86*D86*K86) -> 0 | O86: =P86*K86 -> 0 | P86: {=INDEX($B$111:$AF$131,MATCH($B86,$B$111:$B$131,0),COLUMN($AA$111)+1)} -> 86.32 | Q86: =SUM(N86:O86) -> 0 | X86: =[3]采购参数!A7 -> 那荷 | Y86: =[3]采购参数!B7 -> 1600 | Z86: =[3]采购参数!C7 -> 8.4290499 | AA86: =[3]采购参数!D7 -> 72.872681 | AB86: =[3]采购参数!E7 -> 0.31577618 | AC86: =[3]采购参数!F7 -> 55 | AD86: =[3]采购参数!G7 -> 那荷 | AE86: =[3]采购参数!H7 -> 1600 | ... AI86: =[3]采购参数!L7 -> 55
A87: =AP337*100 -> 0 | B87: =$B$124 -> 烟煤50备 | C87: =INDEX($B$111:$Q$131,MATCH($B87,$B$111:$B$131,0),MATCH(C$2,$B$111:$Q$111,0)) -> 5000 | D87: {=INDEX($B$111:$Q$131,MATCH($B87,$B$111:$B$131,0),COLUMN($D$2)+1)} -> 0 | E87: =C87*D87 -> 0 | F87: =INDEX($B$111:$Q$131,MATCH($B87,$B$111:$B$131,0),MATCH(F$2,$B$111:$Q$111,0)) -> 0 | G87: =INDEX($B$111:$Q$131,MATCH($B87,$B$111:$B$131,0),MATCH(G$2,$B$111:$Q$111,0)) -> 0 | H87: =INDEX($B$111:$Q$131,MATCH($B87,$B$111:$B$131,0),MATCH(H$2,$B$111:$Q$111,0)) -> 0 | I87: =INDEX($B$111:$Q$131,MATCH($B87,$B$111:$B$131,0),MATCH(I$2,$B$111:$Q$111,0)) -> 0 | J87: =IFERROR(K87/K90*100,) -> 0 | K87: 0 | L87: 0 | M87: 0 | N87: =IF(P87>0,INDEX($B$111:$Z$131,MATCH(B87,$B$111:$B$131,0),MATCH($Z$111,$B$111:$Z$111,0))*C87*K87,C87*D87*K87) -> 0 | O87: =P87*K87 -> 0 | P87: {=INDEX($B$111:$AF$131,MATCH($B87,$B$111:$B$131,0),COLUMN($AA$111)+1)} -> 0 | Q87: =SUM(N87:O87) -> 0 | X87: =[3]采购参数!A8 -> 褐煤20-1 | Y87: =[3]采购参数!B9 -> 2000 | Z87: =[3]采购参数!C9 -> 20 | AA87: =[3]采购参数!D9 -> 55 | AB87: =[3]采购参数!E9 -> 1 | AC87: =[3]采购参数!F9 -> 50 | AD87: =[3]采购参数!G8 -> 褐煤20-1 | AE87: =[3]采购参数!H8 -> 2000 | AF87: =[3]采购参数!I8 -> 55 | AG87: =[3]采购参数!J8 -> 15 | AH87: =[3]采购参数!K8 -> 1 | AI87: =[3]采购参数!L8 -> 30
A88: 汽机热耗率 | B88: =$B$125 -> 烟煤55备 | C88: =INDEX($B$111:$Q$131,MATCH($B88,$B$111:$B$131,0),MATCH(C$2,$B$111:$Q$111,0)) -> 5500 | D88: {=INDEX($B$111:$Q$131,MATCH($B88,$B$111:$B$131,0),COLUMN($D$2)+1)} -> 0 | E88: =C88*D88 -> 0 | F88: =INDEX($B$111:$Q$131,MATCH($B88,$B$111:$B$131,0),MATCH(F$2,$B$111:$Q$111,0)) -> 0 | G88: =INDEX($B$111:$Q$131,MATCH($B88,$B$111:$B$131,0),MATCH(G$2,$B$111:$Q$111,0)) -> 0 | H88: =INDEX($B$111:$Q$131,MATCH($B88,$B$111:$B$131,0),MATCH(H$2,$B$111:$Q$111,0)) -> 0 | I88: =INDEX($B$111:$Q$131,MATCH($B88,$B$111:$B$131,0),MATCH(I$2,$B$111:$Q$111,0)) -> 0 | J88: =IFERROR(K88/K90*100,) -> 0 | K88: 0 | L88: 0 | M88: 0 | N88: =IF(P88>0,INDEX($B$111:$Z$131,MATCH(B88,$B$111:$B$131,0),MATCH($Z$111,$B$111:$Z$111,0))*C88*K88,C88*D88*K88) -> 0 | O88: =P88*K88 -> 0 | P88: {=INDEX($B$111:$AF$131,MATCH($B88,$B$111:$B$131,0),COLUMN($AA$111)+1)} -> 0 | Q88: =SUM(N88:O88) -> 0 | X88: =[3]采购参数!A9 -> 褐煤20 | Y88: =[3]采购参数!B8 -> 2000 | Z88: =[3]采购参数!C8 -> 50 | AA88: =[3]采购参数!D8 -> 10 | AB88: =[3]采购参数!E8 -> 0.5 | AC88: =[3]采购参数!F8 -> 30 | AD88: =[3]采购参数!G9 -> 褐煤20 | AE88: =[3]采购参数!H9 -> 2000 | AF88: =[3]采购参数!I9 -> 35 | AG88: =[3]采购参数!J9 -> 35 | AH88: =[3]采购参数!K9 -> 1.5 | AI88: =[3]采购参数!L9 -> 30
A89: =AP338 -> 0 | B89: =$B$127 -> 石油焦 | C89: =INDEX($B$111:$Q$131,MATCH($B89,$B$111:$B$131,0),MATCH(C$2,$B$111:$Q$111,0)) -> 7256.4478 | D89: {=INDEX($B$111:$Q$131,MATCH($B89,$B$111:$B$131,0),COLUMN($D$2)+1)} -> 0 | E89: =C89*D89 -> 0 | F89: =INDEX($B$111:$Q$131,MATCH($B89,$B$111:$B$131,0),MATCH(F$2,$B$111:$Q$111,0)) -> 0 | G89: =INDEX($B$111:$Q$131,MATCH($B89,$B$111:$B$131,0),MATCH(G$2,$B$111:$Q$111,0)) -> 0 | H89: =INDEX($B$111:$Q$131,MATCH($B89,$B$111:$B$131,0),MATCH(H$2,$B$111:$Q$111,0)) -> 0 | I89: =INDEX($B$111:$Q$131,MATCH($B89,$B$111:$B$131,0),MATCH(I$2,$B$111:$Q$111,0)) -> 0 | J89: =IFERROR(K89/K90*100,) -> 0 | K89: 0 | L89: 0 | M89: 0 | N89: =IF(P89>0,INDEX($B$111:$Z$131,MATCH(B89,$B$111:$B$131,0),MATCH($Z$111,$B$111:$Z$111,0))*C89*K89,C89*D89*K89) -> 0 | O89: =P89*K89 -> 0 | P89: {=INDEX($B$111:$AF$131,MATCH($B89,$B$111:$B$131,0),COLUMN($AA$111)+1)} -> 0 | Q89: =SUM(N89:O89) -> 0 | X89: =[3]采购参数!A10 -> 褐煤22 | Y89: =[3]采购参数!B10 -> 2200 | Z89: =[3]采购参数!C10 -> 20 | AA89: =[3]采购参数!D10 -> 50 | AB89: =[3]采购参数!E10 -> 1.5 | AC89: =[3]采购参数!F10 -> 50 | AD89: =[3]采购参数!G10 -> 褐煤22 | AE89: =[3]采购参数!H10 -> 2200 | ... AI89: =[3]采购参数!L10 -> 30
B90: 加权平均 | C90: =IFERROR(SUMPRODUCT(C75:C89,K75:K89)/SUM(K75:K89),) -> 0 | D90: =IFERROR(SUMPRODUCT(C75:C89,D75:D89,K75:K89)/SUMPRODUCT(C75:C89,K75:K89),) -> 0 | E90: =IFERROR(SUMPRODUCT(C75:C89,E75:E89,K75:K89)/SUMPRODUCT(C75:C89,K75:K89),) -> 0 | F90: =IFERROR(SUMPRODUCT(F75:F89,K75:K89)/SUM(K75:K89),) -> 0 | G90: =IFERROR(SUMPRODUCT(G75:G89,K75:K89)/SUM(K75:K89),) -> 0 | H90: =IFERROR(SUMPRODUCT(H75:H89,K75:K89)/SUM(K75:K89),) -> 0 | I90: =IFERROR(SUMPRODUCT(I75:I89,K75:K89)/SUM(K75:K89),) -> 0 | J90: =IFERROR(SUM(J75:J89),) -> 0 | K90: =IFERROR(SUM(K75:K89),) -> 0 | L90: =SUM(L75:L89) -> 524.55002 | M90: =SUM(M75:M89) -> 0 | N90: =SUM(N75:N89) -> 0 | O90: =SUM(O75:O89) -> 0 | P90: =IFERROR(SUMPRODUCT(P75:P89,K75:K89)/SUM(K75:K89),) -> 0 | Q90: =SUM(Q75:Q89) -> 0 | R90: =SUM(R75:R89) -> 0 | X90: =[3]采购参数!A11 -> 褐煤25 | Y90: =[3]采购参数!B11 -> 2500 | Z90: =[3]采购参数!C11 -> 20 | AA90: =[3]采购参数!D11 -> 45 | AB90: =[3]采购参数!E11 -> 1.2 | AC90: =[3]采购参数!F11 -> 45 | AD90: =[3]采购参数!G11 -> 褐煤25 | AE90: =[3]采购参数!H11 -> 2500 | ... AI90: =[3]采购参数!L11 -> 35
B91: 炉灰占比% | C91: =W$47 -> 90 | D91: 炉灰产量（万吨） | E91: =$K90*$G90/100*C91/100 -> 0 | F91: 炉灰销售% | G91: =W$51 -> 88.08189 | H91: 炉灰销量（万吨） | I91: =E91*G91/100 -> 0 | J91: 炉灰价格（元/吨） | K91: =W$54 -> 20 | L91: 炉灰收入（万元） | M91: =I91*K91 -> 0 | N91: 炉灰税率% | O91: 13 | P91: 税后金额（万元） | Q91: =M91/(1+O91/100) -> 0 | X91: =[3]采购参数!A12 -> 褐煤28 | Y91: =[3]采购参数!B12 -> 2800 | Z91: =[3]采购参数!C12 -> 20 | AA91: =[3]采购参数!D12 -> 45 | AB91: =[3]采购参数!E12 -> 1.2 | AC91: =[3]采购参数!F12 -> 35 | AD91: =[3]采购参数!G12 -> 褐煤28 | AE91: =[3]采购参数!H12 -> 2800 | ... AI91: =[3]采购参数!L12 -> 35
B92: 炉渣占比% | C92: =100-C91 -> 10 | D92: 炉渣产量（万吨） | E92: =$K90*$G90/100*C92/100 -> 0 | F92: 炉渣销售% | G92: =W$52 -> 92.485984 | H92: 炉渣销量（万吨） | I92: =E92*G92/100 -> 0 | J92: 炉渣价格（元/吨） | K92: =W$55 -> 0 | L92: 炉渣收入（万元） | M92: =I92*K92 -> 0 | N92: 炉渣税率% | O92: 13 | P92: 税后金额（万元） | Q92: =M92/(1+O92/100) -> 0 | X92: =[3]采购参数!A13 -> 褐煤30 | Y92: =[3]采购参数!B13 -> 3000 | Z92: =[3]采购参数!C13 -> 18 | AA92: =[3]采购参数!D13 -> 45 | AB92: =[3]采购参数!E13 -> 1.2 | AC92: =[3]采购参数!F13 -> 35 | AD92: =[3]采购参数!G13 -> 褐煤30 | AE92: =[3]采购参数!H13 -> 3000 | ... AI92: =[3]采购参数!L13 -> 35
B93: 氨硫比 | C93: =W$49 -> 1.1067708 | D93: 硫酸铵产量（万吨） | E93: =C94*I97 -> 0 | F93: 硫酸铵销售% | G93: =W$53 -> 98.198126 | H93: 硫酸铵销量（万吨） | I93: =E93*G93/100 -> 0 | J93: 硫酸铵价格（元/吨） | K93: =W$56 -> 600 | L93: 硫酸铵收入（万元） | M93: =I93*K93 -> 0 | N93: 硫酸铵税率% | O93: 13 | P93: 税后金额（万元） | Q93: =M93/(1+O93/100) -> 0 | X93: =[3]采购参数!A14 -> 褐煤35 | Y93: =[3]采购参数!B14 -> 3500 | Z93: =[3]采购参数!C14 -> 18 | AA93: =[3]采购参数!D14 -> 40 | AB93: =[3]采购参数!E14 -> 1.2 | AC93: =[3]采购参数!F14 -> 35 | AD93: =[3]采购参数!G14 -> 褐煤35 | AE93: =[3]采购参数!H14 -> 3500 | ... AI93: =[3]采购参数!L14 -> 35
B94: 硫酸铵液氨比 | C94: =W$50 -> 3.1 | D94: 销售蒸汽（万吨） | E94: =W$62 -> 0 | F94: 炉灰调湿比例% | G94: =W64 -> 20 | H94: 炉灰倒运量（万吨） | I94: =(E91-I91)/(1-G94/100) -> 0 | J94: 炉灰倒运单价（元/吨） | K94: =W$57 -> 0.9 | L94: 炉灰倒运费（万元） | M94: =I94*K94 -> 0 | N94: 炉灰倒运税率% | O94: 6 | P94: 税后金额（万元） | Q94: =M94/(1+O94/100) -> 0 | X94: =[3]采购参数!A15 -> 褐煤40 | Y94: =[3]采购参数!B15 -> 4000 | Z94: =[3]采购参数!C15 -> 18 | AA94: =[3]采购参数!D15 -> 25 | AB94: =[3]采购参数!E15 -> 1 | AC94: =[3]采购参数!F15 -> 35 | AD94: =[3]采购参数!G15 -> 褐煤40 | AE94: =[3]采购参数!H15 -> 4000 | ... AI94: =[3]采购参数!L15 -> 35
D95: 蒸汽单价（元/吨） | E95: =W$63 -> 168 | F95: 炉渣调湿比例% | G95: =W65 -> 35 | H95: 炉渣倒运量（万吨） | I95: =(E92-I92)/(1-G95/100) -> 0 | J95: 炉渣倒运单价（元/吨） | K95: =W$58 -> 0.9 | L95: 炉渣倒运费（万元） | M95: =I95*K95 -> 0 | N95: 炉渣倒运税率% | O95: 6 | P95: 税后金额（万元） | Q95: =M95/(1+O95/100) -> 0 | X95: =[3]采购参数!A16 -> 褐煤45 | Y95: =[3]采购参数!B16 -> 4500 | Z95: =[3]采购参数!C16 -> 18 | AA95: =[3]采购参数!D16 -> 25 | AB95: =[3]采购参数!E16 -> 1 | AC95: =[3]采购参数!F16 -> 35 | AD95: =[3]采购参数!G16 -> 褐煤45 | AE95: =[3]采购参数!H16 -> 4500 | ... AI95: =[3]采购参数!L16 -> 35
D96: 蒸汽收入（万元） | E96: =E94*E95 -> 0 | H96: 硫酸铵倒运量（万吨） | I96: =E93-I93 -> 0 | J96: 硫酸铵倒运单价（元/吨） | K96: =W$59 -> 0 | L96: 硫酸铵倒运费（万元） | M96: =I96*K96 -> 0 | N96: 硫酸铵倒运税率% | O96: 6 | P96: 税后金额（万元） | Q96: =M96/(1+O96/100) -> 0 | X96: =[3]采购参数!A17 -> 褐煤50 | Y96: =[3]采购参数!B17 -> 5000 | Z96: =[3]采购参数!C17 -> 12 | AA96: =[3]采购参数!D17 -> 20 | AB96: =[3]采购参数!E17 -> 1 | AC96: =[3]采购参数!F17 -> 35 | AD96: =[3]采购参数!G17 -> 褐煤50 | AE96: =[3]采购参数!H17 -> 5000 | ... AI96: =[3]采购参数!L17 -> 35
D97: 税率% | E97: 9 | H97: 液氨耗用（万吨） | I97: =H90/100*K90*C93 -> 0 | J97: 液氨单价（元/吨） | K97: =W$60 -> 2950 | L97: 液氨费用（万元） | M97: =I97*K97 -> 0 | N97: 液氨税率% | O97: 13 | P97: 税后金额（万元） | Q97: =M97/(1+O97/100) -> 0 | X97: =[3]采购参数!A18 -> 褐煤55 | Y97: =[3]采购参数!B18 -> 5500 | Z97: =[3]采购参数!C18 -> 12 | AA97: =[3]采购参数!D18 -> 20 | AB97: =[3]采购参数!E18 -> 1 | AC97: =[3]采购参数!F18 -> 35 | AD97: =[3]采购参数!G18 -> 褐煤55 | AE97: =[3]采购参数!H18 -> 5500 | ... AI97: =[3]采购参数!L18 -> 35
D98: 税后蒸汽收入（万元） | E98: =E96/(1+E97/100) -> 0 | H98: 尿素耗用（万吨） | I98: =(0.016*I90+0.09)/100*K90*12%/85%*2.354*0 -> 0 | J98: 尿素单价（元/吨） | K98: =W$61 -> 0 | L98: 尿素费用（万元） | M98: =I98*K98 -> 0 | N98: 尿素税率% | O98: 13 | P98: 税后金额（万元） | Q98: =M98/(1+O98/100) -> 0 | X98: =[3]采购参数!A19 -> 烟煤60 | Y98: =[3]采购参数!B19 -> 6000 | Z98: =[3]采购参数!C19 -> 12 | AA98: =[3]采购参数!D19 -> 20 | AB98: =[3]采购参数!E19 -> 1 | AC98: =[3]采购参数!F19 -> 30 | AD98: =[3]采购参数!G19 -> 烟煤60 | AE98: =[3]采购参数!H19 -> 6000 | ... AI98: =[3]采购参数!L19 -> 30
A99: 四厂 | B99: 加权平均 | C99: =(C18*$K18+C42*$K42+C66*$K66+C90*$K90)/($K99) -> 2918.3809 | D99: =($C18*D18*$K18+$C42*D42*$K42+$C66*D66*$K66+$C90*D90*$K90)/($C18*$K18+$C42*$K42+$C66*$K66+$C90*$K90) -> 0.13665809 | E99: =($C18*E18*$K18+$C42*E42*$K42+$C66*E66*$K66+$C90*E90*$K90)/($C18*$K18+$C42*$K42+$C66*$K66+$C90*$K90) -> 459.46859 | F99: =(F18*$K18+F42*$K42+F66*$K66+F90*$K90)/$K99 -> 15.511524 | G99: =(G18*$K18+G42*$K42+G66*$K66+G90*$K90)/$K99 -> 37.240059 | H99: =(H18*$K18+H42*$K42+H66*$K66+H90*$K90)/$K99 -> 0.82876036 | I99: =(I18*$K18+I42*$K42+I66*$K66+I90*$K90)/$K99 -> 25.398027 | J99: =(J18*$K18+J42*$K42+J66*$K66+J90*$K90)/$K99 -> 100 | K99: =SUM(K18,K42,K66,K90) -> 58.930488 | M99: =SUM(M18,M42,M66,M90) -> 0 | N99: =SUM(N18,N42,N66,N90) -> 21926.896 | O99: =SUM(O18,O42,O66,O90) -> 1575.7816 | P99: =(P18*$K18+P42*$K42+P66*$K66+P90*$K90)/$K99 -> 26.739666 | Q99: =SUM(Q18,Q42,Q66,Q90) -> 23502.678 | X99: =[3]采购参数!A20 -> 石油焦 | Y99: =[3]采购参数!B20 -> 7000 | Z99: =[3]采购参数!C20 -> 12 | AA99: =[3]采购参数!D20 -> 5 | AB99: =[3]采购参数!E20 -> 6 | AC99: =[3]采购参数!F20 -> 8 | AD99: =[3]采购参数!G20 -> 石油焦 | AE99: =[3]采购参数!H20 -> 7000 | ... AI99: =[3]采购参数!L20 -> 8
A101: 单位 | B101: 发电量 | C101: 利润 | D101: 综合单位成本 | I101: 上网电量 | J101: 厂用电率 | K101: 售电单价 | L101: 营业收入 | O101: 经营成本
...

Sheet 煤参数
A1: 矿别及煤种 | B1: 收到基低位发热量 | C1: 收到基全水份 | D1: 收到基灰分 | E1: 收到基全硫 | F1: 收到基挥发份 | G1: 空气干燥基水份 | H1: 空气干燥基灰份 | I1: 空气干燥基全硫 | J1: 空气干燥基挥发份
B2: Qnet,ar 大卡 | C2: Mt.ar% | D2: Aar% | E2: St.ar% | F2: Var% | G2: Mad% | H2: Aad% | I2: St.ad% | J2: Vad%
A3: 东怀 | B3: 2376.38 | C3: 9.05 | D3: =H3*(100-$C3)/(100-$G3) -> 53.753421 | E3: =I3*(100-$C3)/(100-$G3) -> 1.5392982 | F3: =J3*(100-$C3)/(100-$G3) -> 20.240833 | G3: 3.1 | H3: 57.27 | I3: 1.64 | J3: 21.565
A4: 跃进 | B4: 1731.53 | C4: 9.9 | D4: =H4*(100-$C4)/(100-$G4) -> 59.606917 | E4: =I4*(100-$C4)/(100-$G4) -> 0.41611229 | F4: =J4*(100-$C4)/(100-$G4) -> 16.798781 | G4: 3.645 | H4: 63.745 | I4: 0.445 | J4: 17.965
A5: 褐煤2（云）长协 | B5: 2400 | C5: 19.2 | D5: =H5*(100-$C5)/(100-$G5) -> 32.974564 | E5: =I5*(100-$C5)/(100-$G5) -> 0.80500871 | F5: =J5*(100-$C5)/(100-$G5) -> 28.483232 | G5: 8.16 | H5: 37.48 | I5: 0.915 | J5: 32.375
A6: 褐煤3（云）长协 | B6: 3200 | C6: 19.15 | D6: =H6*(100-$C6)/(100-$G6) -> 23.873821 | E6: =I6*(100-$C6)/(100-$G6) -> 0.84706369 | F6: =J6*(100-$C6)/(100-$G6) -> 30.507667 | G6: 9.325 | H6: 26.775 | I6: 0.95 | J6: 34.215
A7: 褐煤3（云） | B7: 3200 | C7: 19.15 | D7: =H7*(100-$C7)/(100-$G7) -> 23.873821 | E7: =I7*(100-$C7)/(100-$G7) -> 0.84706369 | F7: =J7*(100-$C7)/(100-$G7) -> 30.507667 | G7: 9.325 | H7: 26.775 | I7: 0.95 | J7: 34.215
A8: 褐煤32（港1） | B8: 3200 | C8: 45 | D8: =H8*(100-$C8)/(100-$G8) -> 6.7073171 | E8: =I8*(100-$C8)/(100-$G8) -> 0.67073171 | F8: =J8*(100-$C8)/(100-$G8) -> 23.47561 | G8: 18 | H8: 10 | I8: 1 | J8: 35
A9: 褐煤35（港2） | B9: 3500 | C9: 40 | D9: =H9*(100-$C9)/(100-$G9) -> 5.8536585 | E9: =I9*(100-$C9)/(100-$G9) -> 0.73170732 | F9: =J9*(100-$C9)/(100-$G9) -> 25.609756 | G9: 18 | H9: 8 | I9: 1 | J9: 35
A10: 褐煤38（港3） | B10: 3800 | C10: 38 | D10: =H10*(100-$C10)/(100-$G10) -> 6.0487805 | E10: =I10*(100-$C10)/(100-$G10) -> 0.75609756 | F10: =J10*(100-$C10)/(100-$G10) -> 26.463415 | G10: 18 | H10: 8 | I10: 1 | J10: 35
A11: 褐煤47 | B11: 4700 | C11: 27 | D11: =H11*(100-$C11)/(100-$G11) -> 7.1219512 | E11: =I11*(100-$C11)/(100-$G11) -> 0.8902439 | F11: =J11*(100-$C11)/(100-$G11) -> 31.158537 | G11: 18 | H11: 8 | I11: 1 | J11: 35
A12: 烟煤55 | B12: 5500 | C12: 17 | D12: =H12*(100-$C12)/(100-$G12) -> 17.659574 | E12: =I12*(100-$C12)/(100-$G12) -> 0.70638298 | F12: =J12*(100-$C12)/(100-$G12) -> 24.723404 | G12: 6 | H12: 20 | I12: 0.8 | J12: 28
